Workbook

Sheet README
A1: Getaway Collective · Build State
A2: Generated 1 Aug 2026 from the repository at C:\gc-app, commit d58044a
A4: WHAT THIS IS | B4: Every addressable surface, pop-up, notification and email in the platform, with what is built, what is not, and what is waiting on you. The Domain sheet carries the constitutional model: the LLP at the apex, Space / Time / Capital beneath it, Governance as the operating law.
A5: HOW IT WAS MADE | B5: The IA sheet is EXTRACTED, not typed. constants/routes.ts is imported directly and each row's status is read from the generated page file on disk — so this workbook cannot disagree with the application about what exists.
A7: THE SOURCE COLUMN | B7: The single most important column on every sheet after IA. It separates fact from opinion:
A8: Code | B8: Extracted from the repository. Verifiable — the file and line are named.
A9: Doc | B9: Stated in a repository document (WAVE-5-OPEN-QUESTIONS.md, WAVE-6-CHANGELOG.md).
A10: Proposed | B10: MY RECOMMENDATION. Not in the repo, not agreed by you, and not built. Nothing marked Proposed has been decided.
A12: STATUS VALUES
A13: Built | B13: Renders the real interface.
A14: Scaffold | B14: Renders the registry Surface: the assembly's declared sections and rules, not the product. It is deliberately obvious that it is a scaffold — a scaffold that looks finished gets signed off.
A15: Not built | B15: Nothing exists.
A16: Framework | B16: Handled by a Next.js convention file rather than a page (/404 → not-found.tsx).
A18: CELLS YOU EDIT | B18: Yellow. They are on the Decisions and Assets sheets — the Decision / Owner / Due / Status columns. Everything else is derived and will be overwritten when this is regenerated.
A20: WHAT IS NOT HERE | B20: Database, authentication and payments. None of the three exists — every page reads static TypeScript. See the Gaps sheet.

Sheet Summary
A1: Build State · Summary
A2: Every figure is a COUNTIF against the IA sheet. Re-derive by regenerating IA; nothing here is typed.
A4: BY STATUS | E4: Scaffold = renders the registry Surface, which shows the assembly's declared sections and rules. It is the product's outline, not the product.
B5: Count | C5: % of total
A6: Built | B6: =COUNTIF(IA!I$5:I$139,A6) -> 51 | C6: =IFERROR(B6/$B$10,0) -> 0.37777778
A7: Scaffold | B7: =COUNTIF(IA!I$5:I$139,A7) -> 82 | C7: =IFERROR(B7/$B$10,0) -> 0.60740741
A8: Framework | B8: =COUNTIF(IA!I$5:I$139,A8) -> 2 | C8: =IFERROR(B8/$B$10,0) -> 0.014814815
A9: Not built | B9: =COUNTIF(IA!I$5:I$139,A9) -> 0 | C9: =IFERROR(B9/$B$10,0) -> 0
A10: Total | B10: =SUM(B6:B9) -> 135 | C10: =IFERROR(B10/$B$10,0) -> 1
A12: BY ACCESS | E12: Access is DERIVED from the assembly's vantage, not declared per route. Twelve routes override it, and route-lint refuses an override without a stated reason.
B13: Count | C13: % of total
A14: public | B14: =COUNTIF(IA!E$5:E$139,A14) -> 51 | C14: =IFERROR(B14/$B$19,0) -> 0.37777778
A15: identified | B15: =COUNTIF(IA!E$5:E$139,A15) -> 18 | C15: =IFERROR(B15/$B$19,0) -> 0.13333333
A16: accredited | B16: =COUNTIF(IA!E$5:E$139,A16) -> 3 | C16: =IFERROR(B16/$B$19,0) -> 0.022222222
A17: member | B17: =COUNTIF(IA!E$5:E$139,A17) -> 26 | C17: =IFERROR(B17/$B$19,0) -> 0.19259259
A18: office | B18: =COUNTIF(IA!E$5:E$139,A18) -> 37 | C18: =IFERROR(B18/$B$19,0) -> 0.27407407
A19: Total | B19: =SUM(B14:B18) -> 135 | C19: =IFERROR(B19/$B$19,0) -> 1
A21: BY GROUP
B22: Count | C22: % of total
A23: gateway | B23: =COUNTIF(IA!C$5:C$139,A23) -> 37 | C23: =IFERROR(B23/$B$29,0) -> 0.27407407
A24: space | B24: =COUNTIF(IA!C$5:C$139,A24) -> 7 | C24: =IFERROR(B24/$B$29,0) -> 0.051851852
A25: capital | B25: =COUNTIF(IA!C$5:C$139,A25) -> 18 | C25: =IFERROR(B25/$B$29,0) -> 0.13333333
A26: time | B26: =COUNTIF(IA!C$5:C$139,A26) -> 2 | C26: =IFERROR(B26/$B$29,0) -> 0.014814815
A27: member | B27: =COUNTIF(IA!C$5:C$139,A27) -> 42 | C27: =IFERROR(B27/$B$29,0) -> 0.31111111
A28: admin | B28: =COUNTIF(IA!C$5:C$139,A28) -> 29 | C28: =IFERROR(B28/$B$29,0) -> 0.21481481
A29: Total | B29: =SUM(B23:B28) -> 135 | C29: =IFERROR(B29/$B$29,0) -> 1
A31: CROSS-CUT
A32: Public AND built | B32: =COUNTIFS(IA!$E$5:$E$139,"public",IA!$I$5:$I$139,"Built") -> 41 | E32: What a stranger can actually see today.
A33: Public AND scaffold | B33: =COUNTIFS(IA!$E$5:$E$139,"public",IA!$I$5:$I$139,"Scaffold") -> 8 | E33: Public URLs that render an outline. These are indexable — the highest-priority build queue.
A34: Indexable | B34: =COUNTIF(IA!$F$5:$F$139,"yes") -> 51 | E34: Must equal the public count: route-lint refuses an indexable route that is not public.
A35: Office routes with rights | B35: =COUNTIFS(IA!$L$5:$L$139,"<>",IA!$E$5:$E$139,"office") -> 37 | E35: Office routes naming a required right from lib/authority.ts.
A36: Dynamic routes | B36: =COUNTIF(IA!$M$5:$M$139,"<>") -> 29 | E36: Carry at least one [param] segment.
A37: Access overrides | B37: =COUNTIF(IA!$N$5:$N$139,"<>") -> 27 | E37: Each states its reason on the IA sheet.
A39: OTHER SHEETS
A40: Pop-ups built | B40: =COUNTIF(Popups!$F$5:$F$40,"Built") -> 2
A41: Pop-ups deliberately none | B41: =COUNTIF(Popups!$F$5:$F$40,"N/A") -> 1
A42: Pop-ups to build | B42: =COUNTIF(Popups!$F$5:$F$40,"Not built") -> 7
A43: Notifications firing today | B43: =COUNTIF(Notifications!$G$5:$G$60,"Live") -> 1
A44: Notifications to build | B44: =COUNTIF(Notifications!$G$5:$G$60,"Not built") -> 16
A45: Emails live | B45: =COUNTIF(Emails!$G$5:$G$60,"Live") -> 2
A46: Emails to build | B46: =COUNTIF(Emails!$G$5:$G$60,"Not built") -> 16
A47: Open gaps | B47: =COUNTIF(Gaps!$G$5:$G$60,"Open") -> 18
A48: Decisions awaiting you | B48: =COUNTIF(Decisions!$H$5:$H$60,"Open") -> 19
A49: Assets outstanding | B49: =COUNTIF(Assets!$I$5:$I$80,"Not supplied") -> 24
A50: Domain constituents | B50: =COUNTIF(Domain!$D$5:$D$120,"object")+COUNTIF(Domain!$D$5:$D$120,"field")+COUNTIF(Domain!$D$5:$D$120,"derived")+COUNTIF(Domain!$D$5:$D$120,"code")+COUNTIF(Domain!$D$5:$D$120,"registered")+COUNTIF(Domain!$D$5:$D$120,"outOfScope") -> 76
A51: — backed by ratified object/field | B51: =COUNTIF(Domain!$D$5:$D$120,"object")+COUNTIF(Domain!$D$5:$D$120,"field") -> 25
A52: — derived or executable law | B52: =COUNTIF(Domain!$D$5:$D$120,"derived")+COUNTIF(Domain!$D$5:$D$120,"code") -> 10
A53: — registered gaps (§33 queue) | B53: =COUNTIF(Domain!$D$5:$D$120,"registered") -> 38
A54: — out of scope by direction | B54: =COUNTIF(Domain!$D$5:$D$120,"outOfScope") -> 3

Sheet IA
A1: Information Architecture
A2: Every URL in the system. Extracted from constants/routes.ts; Status read from the generated page file on disk. Nothing else in the platform holds a URL — a path not on this sheet does not exist.
A4: Path | B4: Name | C4: Group | D4: Vantage | E4: Access | F4: Indexable | G4: Assembly | H4: Assembly Name | I4: Status | J4: Rendered By | K4: Module | L4: Rights | M4: Params | N4: Access Override — why | O4: Notes
A5: / | B5: Home | C5: gateway | D5: gateway | E5: public | F5: yes | G5: AS-32 | H5: The Public Surface | I5: Built | J5: Root | K5: publicpages | O5: Hero region, then routes into the collection. No figure above the fold.
A6: /403 | B6: Not Permitted | C6: gateway | D6: gateway | E6: public | F6: yes | G6: AS-16 | H6: Signal Lost | I6: Scaffold | J6: Surface (registry scaffold) | O6: Says the viewer may not see it. Never says whether it EXISTS — that distinction leaks the shape of the system to anyone probing it.
A7: /404 | B7: Not Found | C7: gateway | D7: gateway | E7: public | F7: yes | G7: AS-16 | H7: Signal Lost | I7: Framework | O7: No stack trace, no exception name, no auto-redirect. [extract] No page.tsx: Next.js serves this from app/not-found.tsx / app/error.tsx by convention.
A8: /500 | B8: System Error | C8: gateway | D8: gateway | E8: public | F8: yes | G8: AS-16 | H8: Signal Lost | I8: Framework | O8: [extract] No page.tsx: Next.js serves this from app/not-found.tsx / app/error.tsx by convention.
A9: /answers | B9: Answers | C9: gateway | D9: gateway | E9: public | F9: yes | G9: AS-17 | H9: The Knowledge Base | I9: Built | J9: Answers | K9: gatewaypages
A10: /auth/sign-in | B10: Identify | C10: gateway | D10: gateway | E10: public | F10: yes | G10: AS-32 | H10: The Public Surface | I10: Built | J10: Identify | K10: publicpages | O10: No password is ever handled by the design system. Delegated.
A11: /auth/sign-out | B11: Sign Out | C11: gateway | D11: gateway | E11: public | F11: yes | I11: Scaffold | J11: Surface (registry scaffold)
A12: /auth/verify | B12: Verify | C12: gateway | D12: gateway | E12: public | F12: yes | I12: Scaffold | J12: Surface (registry scaffold) | O12: The token arrives as a QUERY parameter, not a path segment, and it is not declared as a param for that reason. It is in the URL at all only because an email link has no other carrier — so it is single-use, short-lived, and stripped from the address bar on arrival. A URL is written to server logs, browser history and referrer headers.
A13: /collection | B13: The Collection | C13: gateway | D13: gateway | E13: public | F13: yes | G13: AS-01 | H13: The Gateway Grid | I13: Built | J13: GatewayGrid | K13: gateway
A14: /collective/gallery | B14: The Evidence Portfolio | C14: gateway | D14: gateway | E14: public | F14: yes | G14: AS-32 | H14: The Public Surface | I14: Built | J14: Evidence | K14: publicpages | O14: PUB.08. Ships empty: every plate must say whether it is a photograph, a render or a drawing, and a portfolio of renders shown as photographs is the commonest misrepresentation in this industry. /gallery (AS-09) is a property gallery and is a different thing; both are retained.
A15: /collective/operators | B15: The Operators | C15: gateway | D15: gateway | E15: public | F15: yes | G15: AS-32 | H15: The Public Surface | I15: Built | J15: Operators | K15: publicpages | O15: PUB.06 — what runs a property, and who is accountable when it does not.
A16: /collective/partners | B16: The Foundation | C16: gateway | D16: gateway | E16: public | F16: yes | G16: AS-32 | H16: The Public Surface | I16: Built | J16: Partners | K16: publicpages | O16: PUB.05 — the independent firms. Ships with functions stated and holders withheld until each engagement is recorded against the vehicle it serves.
A17: /collective/press | B17: The Wire | C17: gateway | D17: gateway | E17: public | F17: yes | G17: AS-32 | H17: The Public Surface | I17: Built | J17: Wire | K17: publicpages | O17: PUB.10 — external coverage. Ships empty and says so; the wireframe's six clippings were quotes attributed to real publications that have not published them.
A18: /communique/request | B18: Request the Dossier | C18: gateway | D18: gateway | E18: public | F18: yes | G18: AS-32 | H18: The Public Surface | I18: Built | J18: Dossier | K18: publicpages | O18: PUB.07 — the intelligence pack. What requesting it creates is stated above the form.
A19: /gallery | B19: Gallery | C19: gateway | D19: gateway | E19: public | F19: yes | G19: AS-09 | H19: The Gallery Frame | I19: Built | J19: Gallery | K19: gatewaypages
A20: /how-it-works | B20: How It Works | C20: gateway | D20: gateway | E20: public | F20: yes | G20: AS-32 | H20: The Public Surface | I20: Built | J20: HowItWorks | K20: publicpages | O20: PUB.02 / PUB.11 — the doctrine, then a hard cut to the arithmetic. Distinct from /how-capital-works, which is the waterfall itself rather than the argument for it.
A21: /journal | B21: The Journal | C21: gateway | D21: gateway | E21: public | F21: yes | G21: AS-30 | H21: The Journal | I21: Built | J21: JournalIndex | K21: documents | O21: Index. Entries newest first; the order is checked at load.
A22: /journal/[slug] | B22: Journal Entry | C22: gateway | D22: gateway | E22: public | F22: yes | G22: AS-30 | H22: The Journal | I22: Built | J22: JournalEntry | K22: documents | M22: slug | O22: One entry. Figures are read from the registries, never typed into the prose.
A23: /legal | B23: Legal | C23: gateway | D23: gateway | E23: public | F23: yes | G23: AS-29 | H23: The Standing Document | I23: Built | J23: DocumentIndex | K23: documents | O23: Index of the standing documents.
A24: /legal/accessibility | B24: Accessibility Statement | C24: gateway | D24: gateway | E24: public | F24: yes | G24: AS-29 | H24: The Standing Document | I24: Built | J24: StandingDoc | K24: documents | O24: States what has been tested and what has not. Currently: contrast computed, no assistive-technology testing performed.
A25: /legal/complaints | B25: Complaints Procedure | C25: gateway | D25: gateway | E25: public | F25: yes | G25: AS-29 | H25: The Standing Document | I25: Built | J25: StandingDoc | K25: documents
A26: /legal/cookies | B26: Cookie Notice | C26: gateway | D26: gateway | E26: public | F26: yes | G26: AS-29 | H26: The Standing Document | I26: Built | J26: StandingDoc | K26: documents
A27: /legal/disclosures | B27: Standing Disclosures | C27: gateway | D27: gateway | E27: public | F27: yes | G27: AS-29 | H27: The Standing Document | I27: Built | J27: StandingDoc | K27: documents | O27: Capital at risk, past performance, no guarantee. Body size, reading tone.
A28: /legal/privacy | B28: Privacy Notice | C28: gateway | D28: gateway | E28: public | F28: yes | G28: AS-29 | H28: The Standing Document | I28: Built | J28: StandingDoc | K28: documents
A29: /legal/terms | B29: Terms and Conditions | C29: gateway | D29: gateway | E29: public | F29: yes | G29: AS-29 | H29: The Standing Document | I29: Built | J29: StandingDoc | K29: documents
A30: /maintenance | B30: Maintenance | C30: gateway | D30: gateway | E30: public | F30: yes | G30: AS-15 | H30: System Status | I30: Scaffold | J30: Surface (registry scaffold)
A31: /portfolio | B31: The Portfolio | C31: gateway | D31: gateway | E31: public | F31: yes | G31: AS-07 | H31: The Portfolio Narrative | I31: Built | J31: Portfolio | K31: gatewaypages
A32: /roles | B32: Open Roles | C32: gateway | D32: gateway | E32: public | F32: yes | G32: AS-18 | H32: Recruitment | I32: Built | J32: Roles | K32: gatewaypages
A33: /roles/[code] | B33: Role | C33: gateway | D33: gateway | E33: public | F33: yes | G33: AS-18 | H33: Recruitment | I33: Built | J33: RoleDetail | K33: gatewaypages | M33: code
A34: /search | B34: Search | C34: gateway | D34: gateway | E34: identified | F34: no | I34: Scaffold | J34: Surface (registry scaffold) | N34: Results are scoped to what the viewer may see, which requires knowing who they are. An anonymous search would either return nothing or leak the index.
A35: /signal | B35: The Signal | C35: gateway | D35: gateway | E35: public | F35: yes | G35: AS-32 | H35: The Public Surface | I35: Built | J35: Signal | K35: publicpages | O35: PUB.09 — the weekly transmission. No tuner gate; the form is simply present.
A36: /space | B36: Space | C36: gateway | D36: gateway | E36: public | F36: yes | G36: AS-32 | H36: The Public Surface | I36: Built | J36: Space | K36: publicpages | O36: The physical product: what is built, from what, and what it takes to keep standing.
A37: /status | B37: System Status | C37: gateway | D37: gateway | E37: public | F37: yes | G37: AS-15 | H37: System Status | I37: Scaffold | J37: Surface (registry scaffold)
A38: /story | B38: Story | C38: gateway | D38: gateway | E38: public | F38: yes | G38: AS-08 | H38: The Story Playback | I38: Built | J38: Story | K38: gatewaypages
A39: /structure | B39: The Vehicle | C39: gateway | D39: gateway | E39: public | F39: yes | G39: AS-32 | H39: The Public Surface | I39: Built | J39: Structure | K39: publicpages | O39: From the PUB.01 footer, which calls it SPV Structure. The constitutional default is an LLP; an SPV needs Board approval per property, and the page says so.
A40: /time | B40: Time | C40: gateway | D40: gateway | E40: public | F40: yes | G40: AS-32 | H40: The Public Surface | I40: Built | J40: Time | K40: publicpages | O40: Entitlement: what it is, what it is not, and when it begins. The wireframe's exchange console is stated as unbuilt rather than described as though it exists.
A41: /voices | B41: Voices | C41: gateway | D41: gateway | E41: public | F41: yes | G41: AS-24 | H41: Testimonials | I41: Built | J41: Testimonials | K41: gateway | O41: Testimonials. No figure, no return, no performance reference — regulated speech.
A42: /collection/[property] | B42: Property | C42: space | D42: space | E42: public | F42: yes | G42: AS-03 | H42: The Property Masthead | I42: Built | J42: PropertyMasthead | K42: gateway | M42: property
A43: /collection/[property]/capital | B43: Capital | C43: space | D43: space | E43: public | F43: yes | G43: AS-03 | H43: The Property Masthead | I43: Built | J43: PropertyMasthead | K43: gateway | M43: property | O43: The Capital LENS at the space vantage. Renders AP-03 and routes to the console; it does not render console disclosure because a tab is labelled Capital.
A44: /collection/[property]/gallery | B44: Gallery | C44: space | D44: space | E44: public | F44: yes | G44: AS-10 | H44: The Gallery Strip | I44: Scaffold | J44: Surface (registry scaffold) | M44: property
A45: /collection/[property]/location | B45: Location | C45: space | D45: space | E45: public | F45: yes | G45: AS-12 | H45: Location Intelligence | I45: Scaffold | J45: Surface (registry scaffold) | M45: property
A46: /collection/[property]/space | B46: Space | C46: space | D46: space | E46: public | F46: yes | G46: AS-03 | H46: The Property Masthead | I46: Built | J46: PropertyMasthead | K46: gateway | M46: property
A47: /collection/[property]/time | B47: Time | C47: space | D47: space | E47: public | F47: yes | G47: AS-03 | H47: The Property Masthead | I47: Built | J47: PropertyMasthead | K47: gateway | M47: property
A48: /flow | B48: SlowSpace Coastal | C48: space | D48: space | E48: public | F48: yes | I48: Built | J48: Offering | K48: flow | O48: Step 1 of 5. The offering at the space vantage: capital stack, six-stage waterfall, governance and programme, each carrying its confidence class.
A49: /capital | B49: Capital Console | C49: capital | D49: capital | E49: office | F49: no | G49: AS-02 | H49: The Property Console | I49: Scaffold | J49: Surface (registry scaffold) | L49: portfolio.manage
A50: /capital/calls | B50: Capital Calls | C50: capital | D50: member | E50: member | F50: no | G50: AS-26 | H50: The Capital Call | I50: Scaffold | J50: Surface (registry scaffold) | L50: capital.call
A51: /capital/distributions | B51: Distributions | C51: capital | D51: capital | E51: office | F51: no | G51: AS-02 | H51: The Property Console | I51: Scaffold | J51: Surface (registry scaffold) | L51: distribution.execute
A52: /capital/distributions/[ref] | B52: Distribution | C52: capital | D52: capital | E52: office | F52: no | G52: AS-02 | H52: The Property Console | I52: Scaffold | J52: Surface (registry scaffold) | L52: distribution.execute | M52: ref
A53: /capital/offerings | B53: Offerings | C53: capital | D53: capital | E53: office | F53: no | G53: AS-02 | H53: The Property Console | I53: Scaffold | J53: Surface (registry scaffold) | L53: offering.open
A54: /capital/properties | B54: Properties | C54: capital | D54: capital | E54: office | F54: no | G54: AS-02 | H54: The Property Console | I54: Scaffold | J54: Surface (registry scaffold) | L54: portfolio.manage
A55: /capital/properties/[id] | B55: Property Console | C55: capital | D55: capital | E55: office | F55: no | G55: AS-02 | H55: The Property Console | I55: Scaffold | J55: Surface (registry scaffold) | L55: portfolio.manage | M55: id
A56: /capital/properties/[id]/programme | B56: Programme | C56: capital | D56: capital | E56: office | F56: no | G56: AS-11 | H56: The Stage Progression | I56: Scaffold | J56: Surface (registry scaffold) | L56: property.advance_lifecycle | M56: id
A57: /capital/properties/[id]/valuations | B57: Valuations | C57: capital | D57: capital | E57: office | F57: no | G57: AS-02 | H57: The Property Console | I57: Scaffold | J57: Surface (registry scaffold) | L57: valuation.record | M57: id
A58: /capital/risk | B58: Risk Register | C58: capital | D58: capital | E58: office | F58: no | G58: AS-28 | H58: The Risk Register | I58: Scaffold | J58: Surface (registry scaffold) | L58: compliance.record
A59: /capital/waterfall | B59: Waterfall | C59: capital | D59: capital | E59: office | F59: no | G59: AS-04 | H59: The Capital Explainer | I59: Built | J59: CapitalExplainer | K59: gateway | L59: distribution.execute
A60: /commit/[offering] | B60: Commit | C60: capital | D60: capital | E60: accredited | F60: no | G60: AS-06 | H60: The Commitment Flow | I60: Scaffold | J60: Surface (registry scaffold) | M60: offering | N60: An Investor commits BEFORE membership exists — the Member Law fires on settlement, not here. Requiring member access would make it unreachable by anyone who could use it.
A61: /commit/[offering]/execute | B61: Execute | C61: capital | D61: capital | E61: accredited | F61: no | G61: AS-19 | H61: The Ledger Lock | I61: Scaffold | J61: Surface (registry scaffold) | M61: offering | N61: The execution sequence for a commitment made before membership exists.
A62: /commit/[offering]/risk | B62: Risk Disclosure | C62: capital | D62: capital | E62: accredited | F62: no | G62: AS-14 | H62: The Risk Disclosure | I62: Scaffold | J62: Surface (registry scaffold) | M62: offering | N62: The gate immediately before commitment, on the same path and for the same reason.
A63: /flow/commit | B63: Commit | C63: capital | D63: capital | E63: public | F63: yes | I63: Built | J63: Commit | K63: flow | N63: A worked demonstration of the whole arc, on illustrative data for a fictional partner rather than a real position. Public because the point is that a prospective investor can see every step - including the accreditation and disclosure they would meet later - before committing to any of it. | O63: Step 4. The piston, 3000ms linear. States Committed, never Member.
A64: /flow/risk | B64: Risk Disclosure | C64: capital | D64: capital | E64: public | F64: yes | I64: Built | J64: RiskDisclosure | K64: flow | N64: A worked demonstration of the whole arc, on illustrative data for a fictional partner rather than a real position. Public because the point is that a prospective investor can see every step - including the accreditation and disclosure they would meet later - before committing to any of it. | O64: Step 3. Seven clauses in severity order, on paper. The gate opens on reaching the end by any route.
A65: /how-capital-works | B65: How Capital Works | C65: capital | D65: capital | E65: public | F65: yes | G65: AS-04 | H65: The Capital Explainer | I65: Built | J65: CapitalExplainer | K65: gateway | N65: The waterfall explainer is the single most important thing a prospective investor can read before committing, and putting it behind a sign-in would mean the disclosure only reaches people who have already decided.
A66: /legal/risk-disclosure | B66: Risk Disclosure | C66: capital | D66: capital | E66: public | F66: yes | G66: AS-14 | H66: The Risk Disclosure | I66: Built | J66: StandingDoc | K66: documents | N66: It gates commitment, and it is also the document a prospective investor most needs to read before deciding whether to start. Public to read; the ACKNOWLEDGEMENT still requires identity and is recorded against a version.
A67: /member/entitlement | B67: Entitlement | C67: time | D67: time | E67: member | F67: no | G67: AS-25 | H67: The Time Ledger | I67: Scaffold | J67: Surface (registry scaffold)
A68: /member/entitlement/[year] | B68: Entitlement Year | C68: time | D68: time | E68: member | F68: no | G68: AS-25 | H68: The Time Ledger | I68: Scaffold | J68: Surface (registry scaffold) | M68: year
A69: /flow/accreditation | B69: Accreditation | C69: member | D69: member | E69: public | F69: yes | I69: Built | J69: Accreditation | K69: flow | N69: A worked demonstration of the whole arc, on illustrative data for a fictional partner rather than a real position. Public because the point is that a prospective investor can see every step - including the accreditation and disclosure they would meet later - before committing to any of it. | O69: Step 2. PR-01, resumable - each field saves on blur to a draft record.
A70: /flow/settled | B70: Settled | C70: member | D70: member | E70: public | F70: yes | I70: Built | J70: Settled | K70: flow | N70: A worked demonstration of the whole arc, on illustrative data for a fictional partner rather than a real position. Public because the point is that a prospective investor can see every step - including the accreditation and disclosure they would meet later - before committing to any of it. | O70: Step 5. The first screen where the Member Law has fired.
A71: /member | B71: Your Position | C71: member | D71: member | E71: member | F71: no | G71: AS-05 | H71: The Member Console | I71: Scaffold | J71: Surface (registry scaffold)
A72: /member/calibration | B72: Unit Calibration | C72: member | D72: member | E72: member | F72: no | G72: AS-33 | H72: The Member Surface | I72: Built | J72: Calibration | K72: memberpages | O72: MEM.05. Every control is real and none can be transmitted: the property is at pre-construction, so there is no management system to reach.
A73: /member/calls | B73: Capital Calls | C73: member | D73: member | E73: member | F73: no | G73: AS-26 | H73: The Capital Call | I73: Scaffold | J73: Surface (registry scaffold)
A74: /member/calls/[ref] | B74: Capital Call | C74: member | D74: member | E74: member | F74: no | G74: AS-26 | H74: The Capital Call | I74: Scaffold | J74: Surface (registry scaffold) | M74: ref | O74: Default consequences render in full above the payment control.
A75: /member/codex | B75: The Codex | C75: member | D75: member | E75: member | F75: no | G75: AS-33 | H75: The Member Surface | I75: Built | J75: Codex | K75: memberpages | O75: MEM.07. The manual for one property. The conduct-linked forced buyback the source specifies is marked as not drafted and not in force.
A76: /member/distributions | B76: Distributions | C76: member | D76: member | E76: member | F76: no | G76: AS-05 | H76: The Member Console | I76: Scaffold | J76: Surface (registry scaffold)
A77: /member/distributions/[ref] | B77: Distribution | C77: member | D77: member | E77: member | F77: no | G77: AS-05 | H77: The Member Console | I77: Scaffold | J77: Surface (registry scaffold) | M77: ref
A78: /member/documents | B78: Documents | C78: member | D78: member | E78: member | F78: no | G78: AS-05 | H78: The Member Console | I78: Scaffold | J78: Surface (registry scaffold)
A79: /member/documents/[id] | B79: Document | C79: member | D79: member | E79: member | F79: no | G79: AS-05 | H79: The Member Console | I79: Scaffold | J79: Surface (registry scaffold) | M79: id
A80: /member/holdings | B80: Holdings | C80: member | D80: space | E80: public | F80: yes | G80: AS-10 | H80: The Gallery Strip | I80: Scaffold | J80: Surface (registry scaffold)
A81: /member/holdings/[property] | B81: Holding | C81: member | D81: space | E81: public | F81: yes | G81: AS-03 | H81: The Property Masthead | I81: Built | J81: PropertyMasthead | K81: gateway | M81: property
A82: /member/notifications | B82: Notifications | C82: member | D82: member | E82: member | F82: no | I82: Scaffold | J82: Surface (registry scaffold) | O82: The alert centre. A system ticker (SIGNAL_APERTURE) never lands here; only things asked of the member do.
A83: /member/pass | B83: Access Credentials | C83: member | D83: member | E83: member | F83: no | G83: AS-33 | H83: The Member Surface | I83: Built | J83: Pass | K83: memberpages | O83: MEM.08. Issuing spends your nights and puts the visitor's conduct on your record.
A84: /member/position | B84: Position | C84: member | D84: member | E84: member | F84: no | G84: AS-05 | H84: The Member Console | I84: Scaffold | J84: Surface (registry scaffold)
A85: /member/profile | B85: Passport | C85: member | D85: member | E85: member | F85: no | G85: AS-33 | H85: The Member Surface | I85: Built | J85: Passport | K85: memberpages
A86: /member/reports | B86: Reports | C86: member | D86: member | E86: member | F86: no | G86: AS-05 | H86: The Member Console | I86: Scaffold | J86: Surface (registry scaffold)
A87: /member/resolutions | B87: Resolutions | C87: member | D87: member | E87: member | F87: no | G87: AS-33 | H87: The Member Surface | I87: Built | J87: Boardroom | K87: memberpages
A88: /member/resolutions/[ref] | B88: Ballot | C88: member | D88: member | E88: member | F88: no | G88: AS-27 | H88: The Ballot | I88: Scaffold | J88: Surface (registry scaffold) | M88: ref | O88: Sealed at every vantage. The confirmation never echoes the choice.
A89: /member/settings | B89: Settings | C89: member | D89: member | E89: member | F89: no | I89: Scaffold | J89: Surface (registry scaffold)
A90: /member/settings/notifications | B90: Notification Settings | C90: member | D90: member | E90: member | F90: no | I90: Scaffold | J90: Surface (registry scaffold)
A91: /member/settings/security | B91: Security | C91: member | D91: member | E91: member | F91: no | I91: Scaffold | J91: Surface (registry scaffold)
A92: /member/settings/tax | B92: Tax Details | C92: member | D92: member | E92: member | F92: no | I92: Scaffold | J92: Surface (registry scaffold)
A93: /member/signal | B93: The Signal | C93: member | D93: member | E93: member | F93: no | G93: AS-33 | H93: The Member Surface | I93: Built | J93: SignalLog | K93: memberpages | O93: MEM.06. A written, asynchronous record with the operating partner. No presence indicator and no typing state — both promise an immediacy the queue does not have.
A94: /passport | B94: Your Passport | C94: member | D94: member | E94: identified | F94: no | I94: Scaffold | J94: Surface (registry scaffold) | N94: The passport is how someone BECOMES a member. Requiring membership to reach it would close the only door into the system.
A95: /passport/accreditation | B95: Passport · accreditation | C95: member | D95: capital | E95: identified | F95: no | G95: AS-06 | H95: The Commitment Flow | I95: Scaffold | J95: Surface (registry scaffold) | N95: Accreditation is reached before membership exists, by definition — the Member Law fires on settlement, and settlement cannot happen until accreditation has. Requiring member access here would close the only door into the system.
A96: /passport/address | B96: Passport · address | C96: member | D96: capital | E96: identified | F96: no | G96: AS-06 | H96: The Commitment Flow | I96: Scaffold | J96: Surface (registry scaffold) | N96: Accreditation is reached before membership exists, by definition — the Member Law fires on settlement, and settlement cannot happen until accreditation has. Requiring member access here would close the only door into the system.
A97: /passport/annual-review | B97: Passport · annual review | C97: member | D97: capital | E97: identified | F97: no | G97: AS-06 | H97: The Commitment Flow | I97: Scaffold | J97: Surface (registry scaffold) | N97: Accreditation is reached before membership exists, by definition — the Member Law fires on settlement, and settlement cannot happen until accreditation has. Requiring member access here would close the only door into the system.
A98: /passport/decision | B98: Passport · decision | C98: member | D98: capital | E98: identified | F98: no | G98: AS-06 | H98: The Commitment Flow | I98: Scaffold | J98: Surface (registry scaffold) | N98: Accreditation is reached before membership exists, by definition — the Member Law fires on settlement, and settlement cannot happen until accreditation has. Requiring member access here would close the only door into the system.
A99: /passport/discover | B99: Passport · discover | C99: member | D99: capital | E99: identified | F99: no | G99: AS-06 | H99: The Commitment Flow | I99: Scaffold | J99: Surface (registry scaffold) | N99: Accreditation is reached before membership exists, by definition — the Member Law fires on settlement, and settlement cannot happen until accreditation has. Requiring member access here would close the only door into the system. | O99: Stage 1 of 16. Resumable — each field autosaves on blur to a draft record, which is what makes PR-01 genuinely resumable rather than a second mechanism.
A100: /passport/documents | B100: Passport · documents | C100: member | D100: capital | E100: identified | F100: no | G100: AS-06 | H100: The Commitment Flow | I100: Scaffold | J100: Surface (registry scaffold) | N100: Accreditation is reached before membership exists, by definition — the Member Law fires on settlement, and settlement cannot happen until accreditation has. Requiring member access here would close the only door into the system.
A101: /passport/eligibility | B101: Passport · eligibility | C101: member | D101: capital | E101: identified | F101: no | G101: AS-06 | H101: The Commitment Flow | I101: Scaffold | J101: Surface (registry scaffold) | N101: Accreditation is reached before membership exists, by definition — the Member Law fires on settlement, and settlement cannot happen until accreditation has. Requiring member access here would close the only door into the system.
...

Sheet Popups
A1: Pop-ups, Modals & Dialogs
A2: Two are built. The rest are proposed — read the Source column before treating any row as agreed. Every modal in this system closes on Escape AND on the backdrop, and its close control says Close, never Agree: a dialog whose only exit is 'I agree' collects consent from people trying to get rid of it.
A4: ID | B4: Where | C4: Trigger | D4: What it does | E4: Ground | F4: Status | G4: Source | H4: Notes
A5: P-01 | B5: /flow/accreditation | C5: Read the Terms and Conditions button | D5: Renders the full T&C document over the form. Gates the agreement checkbox — the box enables only once the document has been opened. | E5: Paper | F5: Built | G5: Code | H5: app/_assemblies/flow.tsx:577. Opens IN PLACE rather than linking away: a link loses the half-filled application. Does NOT require scrolling to the end — scroll position is not reading, and a keyboard user never fires a scroll handler.
A6: P-02 | B6: /gallery | C6: Click a frame | D6: Lightbox. Arrow keys step, Escape closes, close control always visible. | E6: Void | F6: Built | G6: Code | H6: app/_assemblies/gatewaypages.tsx:229. Close is never hover-revealed and never in a vanishing corner.
A7: P-03 | B7: All pages | C7: First visit | D7: Cookie / consent banner. | E7: Paper | F7: Not built | G7: Proposed | H7: /legal/cookies exists as a document with no banner in front of it. REQUIRED for DPDP and GDPR if you take EU traffic. Must default to declining non-essential.
A8: P-04 | B8: /flow/accreditation | C8: Navigating away mid-form | D8: Unsaved-changes guard. | E8: Paper | F8: Not built | G8: Proposed | H8: The form autosaves on blur, so this is lower risk than usual — but a half-finished PAN field is lost on a back button today.
A9: P-05 | B9: Any authenticated surface | C9: Session nearing expiry | D9: Session-expiry warning with an extend control. | E9: Paper | F9: Not built | G9: Proposed | H9: Blocked: no authentication exists. Build with Clerk, not before.
A10: P-06 | B10: /member/resolutions | C10: Cast a vote | D10: Vote confirmation. Contribution-weighted, irreversible, and states the weight being cast. | E10: Paper | F10: Not built | G10: Proposed | H10: A vote is irreversible under §24a. It needs the same deliberation treatment as the commitment piston, not an OK button.
A11: P-07 | B11: /admin/media | C11: Upload | D11: File picker with type, dimension and licence capture. | E11: Paper | F11: Not built | G11: Proposed | H11: The media admin surface is built; the upload path is not. Blocked on Vercel Blob.
A12: P-08 | B12: /admin/vehicles/new | C12: Submit formation | D12: Confirm-before-create for a new LLP. | E12: Paper | F12: Not built | G12: Proposed | H12: Creates a constitutional entity. Should require a resolution reference, not a click.
A13: P-09 | B13: Global | C13: A destructive admin action | D13: Confirm-destructive dialog. Types the object name to confirm. | E13: Paper | F13: Not built | G13: Proposed | H13: No destructive admin action is wired yet, so nothing is at risk today.
A14: P-10 | B14: /flow/commit | C14: — | D14: NONE, deliberately. | E14: — | F14: N/A | G14: Code | H14: The commitment is a 3-second sustained press (the piston), not a dialog. The duration IS the deliberation. A confirm dialog after a hold would be two confirmations, which trains people to dismiss both.

Sheet Notifications
A1: In-Product Notifications
A2: Two routes exist to HOLD notifications; no notification is generated by anything. Every row below is Proposed unless marked otherwise. The trigger column names the event — a notification without a named event is a notification nobody can test.
A4: ID | B4: Event that fires it | C4: Message | D4: Audience | E4: Urgency | F4: Where it lands | G4: Status | H4: Source | I4: Notes
A5: N-00 | B5: — | C5: (the surfaces that hold them) | D5: Member | E5: — | F5: /member/notifications, /member/settings/notifications | G5: Scaffold | H5: Code | I5: Both routes exist and render the registry Surface. Nothing writes to them.
A6: N-01 | B6: Accreditation submitted | C6: Application received. A decision follows within 15 working days. | D6: Applicant | E6: Normal | F6: Email + in-product | G6: Not built | H6: Proposed | I6: PR-01 states the window; nothing currently confirms receipt.
A7: N-02 | B7: Accreditation decided | C7: Accreditation approved / declined, with the reason. | D7: Applicant | E7: High | F7: Email + in-product | G7: Not built | H7: Proposed | I7: A decline must state a reason and a route to appeal.
A8: N-03 | B8: Deposit received | C8: ₹50,000 received. It holds your position; it does not make you a partner. | D8: Investor | E8: High | F8: Email + in-product | G8: Not built | H8: Proposed | I8: Must repeat the Member Law. The commonest misreading of a deposit is that it completes the purchase.
A9: N-04 | B9: Completion window opening | C9: Balance and Vehicle Agreement due within 15 working days. | D9: Investor | E9: High | F9: Email | G9: Not built | H9: Proposed | I9: Needs a countdown, and a second at T-3 days.
A10: N-05 | B10: SETTLEMENT | C10: You are a Member of <vehicle>. Entitlement and governance rights begin now. | D10: Member | E10: Critical | F10: Email + in-product | G10: Not built | H10: Proposed | I10: THE MEMBER LAW (I-08) fires here and only here. This is the single most important notification in the system and it is irreversible.
A11: N-06 | B11: Resolution opened | C11: A resolution is open for your vote. Threshold: ordinary / special. Closes <date>. | D11: Member | E11: High | F11: Email + in-product | G11: Not built | H11: Proposed | I11: Must state the threshold and the voting weight, per §24a.
A12: N-07 | B12: Resolution closing | C12: Your vote has not been cast. Voting closes in 48 hours. | D12: Member | E12: High | F12: Email + in-product | G12: Not built | H12: Proposed | I12: A tie is NOT approval, so an uncast vote has a real consequence and the reminder must say so.
A13: N-08 | B13: Resolution decided | C13: Outcome, the count, and the threshold it met. | D13: Member | E13: Normal | F13: Email + in-product | G13: Not built | H13: Proposed | I13: ADR-0008: secret ballot, transparent outcome. Publish the tally, never who voted how.
A14: N-09 | B14: Distribution declared | C14: <amount> declared for the period ending <date>. | D14: Member | E14: Normal | F14: Email + in-product | G14: Not built | H14: Proposed | I14: Must carry a confidence class like every other figure.
A15: N-10 | B15: Distribution paid | C15: <amount> paid to the account ending <n>. | D15: Member | E15: Normal | F15: Email + in-product | G15: Not built | H15: Proposed
A16: N-11 | B16: Distribution BLOCKED | C16: No distribution this period. Stage six does not run if the reserve would fall below its floor. | D16: Member | E16: High | F16: Email + in-product | G16: Not built | H16: Proposed | I16: Silence here reads as an error. A profitable period with no distribution is normal and must be explained when it happens, not in a FAQ.
A17: N-12 | B17: Entitlement opens | C17: Your <n> nights for <year> are now drawable. | D17: Member | E17: Normal | F17: In-product | G17: Not built | H17: Proposed | I17: Not before handover — nothing is drawable against an unbuilt asset.
A18: N-13 | B18: Entitlement expiring | C18: <n> nights lapse on <date>. | D18: Member | E18: Normal | F18: Email + in-product | G18: Not built | H18: Proposed | I18: Needs a stated lapse policy first — see Decisions D-07.
A19: N-14 | B19: Document version changed | C19: <document> is now v<n>. What changed: <summary>. | D19: Member | E19: High | F19: Email | G19: Not built | H19: Proposed | I19: A binding document changing under someone silently is the failure mode. Must link the diff.
A20: N-15 | B20: Covenant proximity | C20: DSCR approaching the covenant threshold. | D20: Office | E20: Critical | F20: In-product | G20: Not built | H20: Proposed | I20: Office vantage only. Never shown at member vantage without Board sign-off on the wording.
A21: N-16 | B21: Valuation published | C21: <property> revalued to <amount> by <source>. | D21: Member | E21: Normal | F21: In-product | G21: Not built | H21: Proposed | I21: Must name the source and its confidence class; a management estimate is not an appraisal.
A22: N-17 | B22: Lead captured | C22: A signal / dossier request arrived. | D22: Office | E22: Low | F22: Email | G22: Live | H22: Code | I22: The only notification that actually fires today. app/api/signal, app/api/dossier → lib/leads.ts.

Sheet Emails
A1: Transactional Email
A2: Two endpoints are live via Resend; both return 503 without RESEND_API_KEY and the page says so rather than showing a false success. Everything else is proposed. No template system, no unsubscribe handling and no verified sending domain exists yet.
A4: ID | B4: Trigger | C4: To | D4: Subject / purpose | E4: Type | F4: Template | G4: Status | H4: Source | I4: Notes
A5: E-01 | B5: /signal form submit | C5: SIGNAL_LEAD_EMAIL | D5: New Signal subscriber | E5: Internal | F5: Plain text | G5: Live | H5: Code | I5: lib/leads.ts. Returns 503 when unconfigured; the form renders an honest failure with a mailto fallback.
A6: E-02 | B6: /communique/request submit | C6: DOSSIER_LEAD_EMAIL | D6: New dossier request | E6: Internal | F6: Plain text | G6: Live | H6: Code | I6: Same path. 400 on invalid input, 503 on unconfigured.
A7: E-03 | B7: Signal form submit | C7: The subscriber | D7: Confirm the subscription (double opt-in) | E7: Outbound | F7: — | G7: Not built | H7: Proposed | I7: REQUIRED. Today you capture an address and send that person nothing — no confirmation and no way to unsubscribe. This is a compliance gap, not a nicety.
A8: E-04 | B8: Dossier request | C8: The requester | D8: The dossier itself | E8: Outbound | F8: — | G8: Not built | H8: Proposed | I8: The form promises an intelligence pack. Nothing sends one. See Assets A-20.
A9: E-05 | B9: Sign-up | C9: New account | D9: Verify your email address | E9: Outbound | F9: — | G9: Not built | H9: Proposed | I9: Blocked on Clerk, which handles this natively.
A10: E-06 | B10: Accreditation submitted | C10: Applicant | D10: Application received · 15 working days | E10: Outbound | F10: — | G10: Not built | H10: Proposed | I10: Pairs with N-01.
A11: E-07 | B11: Accreditation decided | C11: Applicant | D11: Decision, with reason | E11: Outbound | F11: — | G11: Not built | H11: Proposed | I11: Pairs with N-02.
A12: E-08 | B12: Deposit received | C12: Investor | D12: ₹50,000 received · what it does and does not do | E12: Outbound | F12: — | G12: Not built | H12: Proposed | I12: Must state that a deposit makes nobody a partner.
A13: E-09 | B13: Deposit received | C13: Investor | D13: Payment receipt (GST-compliant) | E13: Outbound | F13: — | G13: Not built | H13: Proposed | I13: Tax-document requirements unconfirmed — see Decisions D-05.
A14: E-10 | B14: Settlement | C14: Member | D14: You are a Member of <vehicle> | E14: Outbound | F14: — | G14: Not built | H14: Proposed | I14: THE MEMBER LAW. Should carry the Vehicle Agreement and the register entry as attachments.
A15: E-11 | B15: Resolution opened | C15: Members | D15: A resolution is open · closes <date> | E15: Outbound | F15: — | G15: Not built | H15: Proposed
A16: E-12 | B16: Resolution closing | C16: Non-voters | D16: Voting closes in 48 hours | E16: Outbound | F16: — | G16: Not built | H16: Proposed
A17: E-13 | B17: Resolution decided | C17: Members | D17: Outcome and tally | E17: Outbound | F17: — | G17: Not built | H17: Proposed | I17: Tally yes; individual votes never.
A18: E-14 | B18: Distribution paid | C18: Member | D18: Distribution statement | E18: Outbound | F18: — | G18: Not built | H18: Proposed | I18: Needs a PDF generator — none exists.
A19: E-15 | B19: Quarterly | C19: Members | D19: Vehicle report | E19: Outbound | F19: — | G19: Not built | H19: Proposed | I19: Cadence and content not agreed — Decisions D-08.
A20: E-16 | B20: Document version change | C20: Members | D20: <document> updated to v<n> | E20: Outbound | F20: — | G20: Not built | H20: Proposed | I20: Legally significant. Must link the diff, not just announce it.
A21: E-17 | B21: Weekly | C21: Signal subscribers | D21: The Signal | E21: Marketing | F21: — | G21: Not built | H21: Proposed | I21: Needs unsubscribe, preference centre and a verified domain before a single send.
A22: E-18 | B22: Password reset | C22: Account | D22: Reset your password | E22: Outbound | F22: — | G22: Not built | H22: Proposed | I22: Blocked on Clerk.

Sheet Gaps
A1: Current Gaps
A2: What is missing, why it matters, and what it blocks. Severity is my assessment. 'Blocks launch' means I would not put the URL in front of an investor until it is closed.
A4: ID | B4: Area | C4: The gap | D4: What it blocks | E4: Severity | F4: Effort | G4: Status | H4: Source | I4: Notes
A5: G-01 | B5: Legal | C5: ~9,000 words of Terms and Risk Disclosure have never been reviewed by a lawyer. | D5: Any real investor traffic | E5: Blocks launch | F5: External | G5: Open | H5: Code | I5: content/legal.ts + slowspace.ts. Drafted to be accurate; not drafted to be relied on. This is the single largest exposure on this sheet and it is not a code problem.
A6: G-02 | B6: Legal | C6: Repository is PUBLIC, so the unreviewed copy and the LLP identifiers are world-readable. | D6: — | E6: Blocks launch | F6: Minutes | G6: Open | H6: Code | I6: One command flips it. Raised twice; not yet actioned.
A7: G-03 | B7: Entity | C7: SlowSpace Coastal LLP, LLPIN AAC-4471 and the Udupi registered office are modelled from a dossier, not verified against the MCA register. | D7: Publishing the offering | E7: Blocks launch | F7: External | G7: Open | H7: Code | I7: If the entity is not incorporated with that identifier, the platform is asserting that it is.
A8: G-04 | B8: Auth | C8: No authentication. lib/access.ts fails closed, so 63 member/office routes correctly deny everyone. | D8: Every member and office surface | E8: High | F8: Large | G8: Open | H8: Code | I8: Deliberate and correct for an unfinished system. Clerk is chosen but not integrated.
A9: G-05 | B9: Data | C9: No database. Every page reads static TypeScript. | D9: Persistence of anything | E9: High | F9: Large | G9: Open | H9: Code | I9: Drizzle schema and 27 tables are generated and checked; nothing connects to Neon.
A10: G-06 | B10: Payments | C10: No payment processor. The ₹50,000 deposit cannot be taken. | D10: The commitment flow | E10: High | F10: Large | G10: Open | H10: Code | I10: Razorpay chosen. The piston records a state change in memory and nothing else.
A11: G-07 | B11: Product | C11: 82 of 135 routes render the registry Surface scaffold, not the product. | D11: Depth beyond the built paths | E11: High | F11: Large | G11: Open | H11: Code | I11: See the IA sheet. 12 of these are PUBLIC and indexable — the highest-priority subset.
A12: G-08 | B12: Media | C12: No photography exists. The gallery ships five labelled drawings. | D12: Every visual surface | E12: High | F12: External | G12: Open | H12: Code | I12: content/gateway.ts states this plainly rather than shipping renders as photographs. See the Assets sheet.
A13: G-09 | B13: Ops | C13: No error tracking. | D13: Knowing when production breaks | E13: High | F13: Small | G13: Open | H13: Doc | I13: Sentry identified as the sixth account; not opened.
A14: G-10 | B14: Ops | C14: No rate limiting on /api/signal or /api/dossier. | D14: Publicising the URL | E14: High | F14: Small | G14: Open | H14: Code | I14: Both are public, unauthenticated and send email. Trivially abusable once the domain is known.
A15: G-11 | B15: Compliance | C15: No cookie/consent banner, no unsubscribe, no double opt-in. | D15: EU traffic; any marketing send | E15: High | F15: Medium | G15: Open | H15: Code | I15: /legal/cookies documents a policy nothing enforces.
... A22: G-18 | B22: Ops | C22: Vercel region pinned to bom1 for DPDP residency; plan support unverified. | D22: First deploy | E22: Low | F22: Minutes | G22: Open | H22: Code | I22: vercel.json. Will fail the deploy if the plan disallows region pinning.

Sheet Decisions
A1: Decisions Awaiting You
A2: Each is a decision I could not make for you because it is commercial, fiduciary, legal or a matter of taste. Where I had a defensible default I applied it and said so in My Recommendation — none of those is agreed. YELLOW CELLS ARE YOURS TO FILL.
A4: ID | B4: Area | C4: The decision | D4: My recommendation | E4: Source | F4: Your decision | G4: Owner | H4: Status | I4: Due
A5: D-01 | B5: Legal | C5: Engage a lawyer to review the Terms and Risk Disclosure before any real traffic. Who, and when? | D5: Do this before the domain is public. Nothing else on this sheet costs more to get wrong. | E5: Code | H5: Open
A6: D-02 | B6: Legal | C6: Repository visibility: public or private? | D6: Private until D-01 closes. Search engines cannot un-crawl. | E6: Code | H6: Open
A7: D-03 | B7: Entity | C7: Confirm SlowSpace Coastal LLP is incorporated, and the real LLPIN and registered office. | D7: Replace with placeholders until confirmed, or confirm and keep. | E7: Code | H7: Open
A8: D-04 | B8: Commercial | C8: Minimum unit is 5% and the ceiling 50%. Confirm both. | D8: Keep. 5% admits a wider register; 50% is where a partner would carry every ordinary resolution alone under §24a. | E8: Code | H8: Open
A9: D-05 | B9: Finance | C9: Is the ₹50,000 deposit taxable on receipt, and what document must issue? | D9: Needs your accountant. It changes E-09 and the receipt wording. | E9: Proposed | H9: Open
A10: D-06 | B10: Commercial | C10: Confirm the entitlement pool of 180–210 nights a year for the whole property. | D10: Keep. Derived so that no partition can exceed what the property can deliver. | E10: Code | H10: Open
A11: D-07 | B11: Commercial | C11: Do unused nights lapse, roll over, or convert? | D11: Needs a policy before N-13 can be written. Lapse is simplest and the least generous; say which it is. | E11: Proposed | H11: Open
A12: D-08 | B12: Comms | C12: Reporting cadence to members — quarterly, half-yearly? | D12: Quarterly, aligned to the distribution period. | E12: Proposed | H12: Open
A13: D-09 | B13: Design | C13: Risk categories: extend the design system to 10, or map the registry's 10 onto 8? | D13: Map first (no amendment needed), then extend. | E13: Doc | H13: Open
A14: D-10 | B14: Brand | C14: Brand voice: does L1-02 'Warm' or Addendum A 'never persuades' govern interface copy? | D14: Addendum A governs interface copy; L1-02 governs member-facing narrative. Write it down. | E14: Doc | H14: Open
A15: D-11 | B15: Ops | C15: Confirm the production domain. | D15: getawaycollective.in is assumed throughout .env.example. Every share card and sitemap URL depends on it. | E15: Code | H15: Open
A16: D-12 | B16: Ops | C16: Confirm the Vercel plan supports region pinning to bom1. | D16: Needed for the DPDP residency claim. If not, either upgrade or drop the claim — do not keep the claim without the pinning. | E16: Code | H16: Open
... A23: D-19 | B23: Domain | C23: Confirm the audit-threshold policy: the statutory mirror assumes EVERY GC vehicle crosses ₹25 lakh contribution at formation, so all are audited and ITR-5 falls on 31 October. | D23: True of SlowSpace (₹4 Cr equity). Confirm it holds as standing policy so the mirror never needs a per-vehicle exception. | E23: Code | H23: Open

Sheet Assets
A1: Pending Assets
A2: Nothing here exists. Dimensions are what the code actually consumes; where a surface currently renders a generated placeholder, the placeholder is named so you can see what it is standing in for. YELLOW CELLS ARE YOURS.
A4: ID | B4: Category | C4: Asset | D4: Type | E4: Dimensions | F4: Qty | G4: Used by | H4: Currently renders | I4: Status | J4: Owner | K4: Due
A5: A-01 | B5: Brand | C5: Wordmark | D5: SVG | E5: Vector, 1-colour | F5: 1 | G5: Header, footer, favicon | H5: Text 'GC.SYSTEM' | I5: Not supplied
A6: A-02 | B6: Brand | C6: Monogram / favicon | D6: SVG | E6: Square, legible at 16px | F6: 1 | G6: app/icon.tsx | H6: Generated GC monogram from tokens | I6: Not supplied
A7: A-03 | B7: Brand | C7: Brand guidelines PDF | D7: PDF | E7: — | F7: 1 | G7: Partner and press packs | H7: — | I7: Not supplied
A8: A-04 | B8: Property | C8: SlowSpace Coastal · hero | D8: Photo/render | E8: 3200×1800 (16:9), ≥2× retina | F8: 1 | G8: /flow, /collection/[property] | H8: Generated gradient plate, hue 198 | I8: Not supplied
A9: A-05 | B9: Property | C9: SlowSpace Coastal · gallery set | D9: Photo/render | E9: 2400×3000 (4:5) | F9: 8–12 | G9: /gallery, /collection/[property]/gallery | H9: 2 labelled drawings (F-01, F-02) | I9: Not supplied
A10: A-06 | B10: Property | C10: SlowSpace Coastal · site plan | D10: Drawing | E10: Vector or 3000px wide | F10: 1 | G10: /collection/[property]/location | H10: F-02 placeholder | I10: Not supplied
A11: A-07 | B11: Property | C11: SlowSpace Coastal · section drawings | D11: Drawing | E11: Vector | F11: 3–4 | G11: Space surfaces | H11: F-01 placeholder | I11: Not supplied
A12: A-08 | B12: Property | C12: Kyoto House · gallery set | D12: Photo | E12: 2400×3000 (4:5) | F12: 6–10 | G12: /collection/kyoto-house | H12: 1 labelled drawing (F-03) | I12: Not supplied
A13: A-09 | B13: Property | C13: Swiss Vault · gallery set | D13: Photo | E13: 2400×3000 (4:5) | F13: 6–10 | G13: /collection/swiss-vault | H13: 1 labelled drawing (F-04) | I13: Not supplied
A14: A-10 | B14: Property | C14: Oslo Base · gallery set | D14: Photo | E14: 2400×3000 (4:5) | F14: 6–10 | G14: /collection/oslo-base | H14: 1 labelled drawing (F-05) | I14: Not supplied
A15: A-11 | B15: Property | C15: Aerial / context | D15: Photo | E15: 3200×1800 | F15: 1 per property | G15: Location surfaces | H15: — | I15: Not supplied
A16: A-12 | B16: Social | C16: Default share card | D16: PNG | E16: 1200×630 | F16: 1 | G16: app/opengraph-image.tsx | H16: Generated type-only card from tokens | I16: Not supplied
... A28: A-24 | B28: Legal | C28: Lawyer-reviewed Terms and Risk Disclosure | D28: Text | E28: — | F28: 1 | G28: content/legal.ts | H28: Unreviewed draft, ~9,000 words | I28: Not supplied

Sheet Domain
A1: The Vehicle Domain Model
A2: EXTRACTED from constants/vehicle-domain.ts (commit b0ade3f), not typed. The LLP sits at the apex; Space, Time and Capital are its constituents; Governance is the constitutional layer that governs the other three — not a fourth business function. Every constituent states what backs it: a ratified object, a UFR field, a derivation, executable code, a REGISTERED gap awaiting a §33 amendment, or OUT OF SCOPE with the reason.
A4: Domain | B4: Section | C4: Constituent | D4: Backing | E4: Backed by | F4: Gap / exclusion detail | G4: Note
A5: Space | B5: What does the LLP own?
B6: SP.1 · Property | C6: Property Code | D6: object | E6: Property | G6: The asset code (PDB-01) is carried on the record today; a dedicated UFR entry is the E-06 gap to close when the field is next touched.
B7: SP.1 · Property | C7: Property Name | D7: field | E7: UFR-0060 on Property
B8: SP.1 · Property | C8: Property Type | D8: object | E8: Property | G8: Carried on the Property record; the closed type set is an enum question, not a new object.
B9: SP.1 · Property | C9: Investment Thesis | D9: object | E9: Investment Thesis | G9: An attribute of the asset, constitutionally: the thesis names why THIS property. It moved from Intelligence to Space for that reason.
B10: SP.1 · Property | C10: Asset Status | D10: field | E10: UFR-0066 on Property | G10: The lifecycle field. Pre-construction → construction → stabilised → disposition.
B11: SP.1 · Property | C11: Documents Folder | D11: registered | E11: PropertyDocument | F11: One object per instrument with kind, custody and hash — a folder is not a record.
B12: SP.2 · Fixed Assets | C12: Furniture & Fixtures | D12: registered | E12: FixedAsset | F12: Asset register entries with cost, life, and depreciation basis. Required before the first fit-out invoice lands.
B13: SP.2 · Fixed Assets | C13: Plant & Machinery | D13: registered | E13: FixedAsset | F13: Same object, classed plant_machinery.
B14: SP.2 · Fixed Assets | C14: Renewable Systems | D14: registered | E14: FixedAsset | F14: Same object, classed renewable.
B15: SP.2 · Fixed Assets | C15: Capital Improvements | D15: registered | E15: FixedAsset | F15: Same object, classed improvement — funded from the Sinking Fund, which is why the class must be distinguishable.
B16: SP.3 · Asset Protection | C16: Insurance | D16: registered | E16: InsurancePolicy | F16: Policy, insurer, sum insured, expiry. The governance calendar needs the expiry date to fire a compliance event.
B17: SP.3 · Asset Protection | C17: Valuation | D17: object | E17: Valuation | G17: Already ratified. Carries its source and confidence class — a management estimate is not an appraisal.
B18: SP.4 · Property Documents | C18: Drawings | D18: registered | E18: PropertyDocument | F18: kind: drawing
B19: SP.4 · Property Documents | C19: Approvals | D19: registered | E19: PropertyDocument | F19: kind: approval. CRZ clearance lives here — the compliance mirror in Governance references it.
B20: SP.4 · Property Documents | C20: Manuals | D20: registered | E20: PropertyDocument | F20: kind: manual
B21: SP.4 · Property Documents | C21: Warranties | D21: registered | E21: PropertyDocument | F21: kind: warranty. Expiry-bearing, like insurance — feeds the governance calendar.
B22: SP.4 · Property Documents | C22: Asset Registers | D22: registered | E22: FixedAsset | F22: The register IS the set of FixedAsset records; a separate register document would be a copy that drifts.
A23: Time | B23: How much time does each LLP Partner legally control?
B24: TM.1 · Ownership Calendar | C24: Calendar Year | D24: registered | E24: OwnershipCalendar | F24: One record per vehicle per year. The vehicle-level pool the allocations divide.
B25: TM.1 · Ownership Calendar | C25: Allocation Year | D25: registered | E25: OwnershipCalendar | F25: The year an allocation belongs to — distinct from the calendar year it is used in only once rollover policy exists, which is Decision D-07.
B26: TM.1 · Ownership Calendar | C26: Available Days | D26: derived | E26: NIGHT_POOL stated per vehicle per year; each position takes floor(pool × stake) | G26: The pool is stated for the whole vehicle and each position takes its floor, so the sum of every partner's entitlement can never exceed what the property delivers. Multiplying a per-unit figure would invent nights.
B27: TM.2 · Allocation Rights | C27: Ownership Percentage | D27: field | E27: UFR-0242 on Ownership Position | G27: units_held over total_units_issued. The stake is the input; time is one of its outputs.
B28: TM.2 · Allocation Rights | C28: Annual Day Allocation | D28: derived | E28: floor(available_days × ownership_percentage) | G28: STATIC. It does not vary with usage, season or behaviour — a right attached to ownership, not a reward attached to conduct.
B29: TM.2 · Allocation Rights | C29: Reserved Days | D29: registered | E29: AllocationRight | F29: Days the vehicle withholds from the pool before division — maintenance closures, statutory closures.
B30: TM.2 · Allocation Rights | C30: Blackout Rules | D30: registered | E30: AllocationRight | F30: Vehicle-level rules constraining when allocation may be drawn. Rules, never individual draws.
B31: TM.3 · Usage Rights | C31: Usage Rights | D31: outOfScope | F31: Directed out of scope, 1 Aug 2026. Usage is operation, and operation belongs to the Operating Company. The vehicle records who CONTROLS time, never who USED it.
B32: TM.4 · Calendar Rights | C32: Calendar Rights | D32: outOfScope | F32: Directed out of scope, 1 Aug 2026. Same boundary as Usage Rights.
B33: TM.5 · Time Ledger | C33: Time Ledger | D33: outOfScope | F33: Directed out of scope, 1 Aug 2026. A ledger of draws is an operating record. If it is ever pulled inside the vehicle, it enters as a §33 amendment — not as a quiet table.
A34: Capital | B34: What is the financial position of the LLP?
B35: CP.1 · Investors | C35: Partner Register | D35: object | E35: Investor
B36: CP.1 · Investors | C36: Ownership Register | D36: object | E36: Ownership Position | G36: The same record Time reads its stake from. One register, two domains reading it — never two registers.
B37: CP.1 · Investors | C37: Capital Accounts | D37: registered | E37: CapitalAccount | F37: Per-partner: contributed, share of profit, drawings, closing balance. The LLP Act requires it and Schedule-form accounts assume it.
B38: CP.2 · Capital Formation | C38: Investment Offering | D38: object | E38: Investment Offering
B39: CP.2 · Capital Formation | C39: Commitments | D39: object | E39: Commitment
B40: CP.2 · Capital Formation | C40: Contributions | D40: object | E40: Investment | G40: A settled contribution. The Member Law fires here and nowhere else.
B41: CP.2 · Capital Formation | C41: Capital Calls | D41: object | E41: Capital Call
B42: CP.3 · Finance | C42: Debt | D42: registered | E42: DebtFacility | F42: Lender, principal, rate, moratorium, covenants. The ₹5.5 Cr facility currently lives as prose in slowspace.ts — a covenant nobody can query is a covenant nobody monitors.
B43: CP.3 · Finance | C43: Interest | D43: registered | E43: DebtFacility | F43: Schedule rows on the facility.
B44: CP.3 · Finance | C44: Repayments | D44: registered | E44: DebtFacility | F44: Schedule rows on the facility.
B45: CP.3 · Finance | C45: Banking | D45: registered | E45: BankAccount | F45: Account, bank, signatories. Signing authority itself is Governance — the account is Capital, the authority over it is law.
B46: CP.4 · Revenue | C46: Revenue | D46: registered | E46: LedgerEntry | F46: Recognised revenue, by period and class.
B47: CP.4 · Revenue | C47: Operating Income | D47: registered | E47: LedgerEntry | F47: class: operating
B48: CP.4 · Revenue | C48: Brand Income | D48: registered | E48: LedgerEntry | F48: class: brand
B49: CP.4 · Revenue | C49: Other Income | D49: registered | E49: LedgerEntry | F49: class: other
B50: CP.5 · Expenses | C50: Operating Costs | D50: registered | E50: LedgerEntry | F50: class: operating_cost
B51: CP.5 · Expenses | C51: Asset Management | D51: registered | E51: LedgerEntry | F51: class: asset_management
B52: CP.5 · Expenses | C52: Administration | D52: registered | E52: LedgerEntry | F52: class: administration
B53: CP.5 · Expenses | C53: Insurance | D53: registered | E53: LedgerEntry | F53: class: insurance — the premium is an expense here; the policy is Space (SP.3).
B54: CP.5 · Expenses | C54: Professional Fees | D54: registered | E54: LedgerEntry | F54: class: professional_fees
B55: CP.6 · Reserves | C55: Sinking Fund | D55: code | E55: lib/domain.ts — waterfall stage 4, floor rule F-06 | G55: The reserve exists as executable law: 2.5% of revenue in, distribution blocked if paying would breach the floor. A Reserve record joins when persistence exists.
B56: CP.7 · Valuation | C56: NAV | D56: derived | E56: asset valuations (Space) − debt outstanding + reserves + net working capital | G56: Derived, never typed. The prototype carried four different valuations of one house because each screen held its own copy.
B57: CP.8 · Distribution | C57: Waterfall | D57: code | E57: lib/domain.ts — six stages, closes to 100%, F-05
B58: CP.8 · Distribution | C58: Debt Service | D58: derived | E58: investor share − partner distribution; stage 5, the senior claim
B59: CP.8 · Distribution | C59: Partner Distributions | D59: object | E59: Distribution
B60: CP.8 · Distribution | C60: Retained Earnings | D60: derived | E60: what stage 6 withholds when blocked — retained, never evaporated
B61: CP.9 · Reporting | C61: Balance Sheet | D61: object | E61: Performance Report | G61: Statement kinds on the report object; the statutory filing of them is Governance (Form 8).
B62: CP.9 · Reporting | C62: Profit & Loss | D62: object | E62: Performance Report
B63: CP.9 · Reporting | C63: Cash Flow | D63: object | E63: Performance Report
B64: CP.9 · Reporting | C64: Capital Accounts | D64: registered | E64: CapitalAccount | F64: Reported per partner, per period — same object as CP.1.
B65: CP.9 · Reporting | C65: Forecasts | D65: object | E65: Forecast | G65: Forward-looking, so every figure carries its confidence class.
A66: Governance ⚖ | B66: Under what law does the LLP act, and can it prove compliance?
B67: GV.1 · LLP Governance | C67: LLP Agreement | D67: object | E67: Agreement | G67: The constitutional instrument. Filed as Form 3 within 30 days of incorporation — the statutory mirror row references this record.
B68: GV.1 · LLP Governance | C68: Partner & Designated Partner Register | D68: object | E68: Investor | G68: The register read here is the same Investor set Capital holds — annotated with designated-partner status, never duplicated.
B69: GV.1 · LLP Governance | C69: Authority Matrix | D69: code | E69: lib/authority.ts — rights, roles, separationViolations() | G69: Executable, and checked: no role may hold a dangerous triad. A matrix kept as a document is a matrix nobody enforces.
B70: GV.1 · LLP Governance | C70: Board / Partner Meeting Records | D70: object | E70: Committee
B71: GV.1 · LLP Governance | C71: Resolution Register | D71: object | E71: Resolution
B72: GV.1 · LLP Governance | C72: Voting Register | D72: code | E72: constants/voting.ts — thresholds; ADR-0008 secret ballot, transparent outcome | G72: Contribution-weighted per §24a. Ordinary carries above 50% — a tie is not approval. Special at 76%. Tallies are published; who voted how never is.
B73: GV.1 · LLP Governance | C73: Constitutional Amendments | D73: object | E73: Policy | G73: Including §33 amendments — which is how every `registered` candidate in this file becomes real.
B74: GV.1 · LLP Governance | C74: All Agreements | D74: object | E74: Agreement | G74: Operator agreement, brand licence, facility agreement — one object, kinds distinguished. Every contract the vehicle signs lands here or does not bind it.
B75: GV.2 · Corporate Administration | C75: Incorporation Documents | D75: registered | E75: StatutoryRecord | F75: kind: incorporation — certificate, LLPIN, Form 2.
B76: GV.2 · Corporate Administration | C76: PAN | D76: registered | E76: StatutoryRecord | F76: kind: pan
B77: GV.2 · Corporate Administration | C77: TAN | D77: registered | E77: StatutoryRecord | F77: kind: tan — required the day the first salary or contractor payment is made, for TDS.
B78: GV.2 · Corporate Administration | C78: Registered Office | D78: registered | E78: StatutoryRecord | F78: kind: registered_office. No UFR field carries it today — LLP.office in slowspace.ts is prose. A change of registered office is Form 15; the mirror row exists below.
B79: GV.2 · Corporate Administration | C79: Statutory Registers | D79: registered | E79: StatutoryRecord | F79: kind: register
B80: GV.2 · Corporate Administration | C80: Digital Signatures | D80: registered | E80: StatutoryRecord | F80: kind: dsc — every designated partner needs one before any MCA filing can be made.
B81: GV.2 · Corporate Administration | C81: Banking Authorities | D81: registered | E81: StatutoryRecord | F81: kind: banking_authority — WHO may operate the account. The account itself is Capital (CP.3).
B82: GV.2 · Corporate Administration | C82: Authorised Signatories | D82: registered | E82: StatutoryRecord | F82: kind: signatory
B83: GV.2 · Corporate Administration | C83: Enterprise Policies | D83: object | E83: Policy
B84: GV.2 · Corporate Administration | C84: Governance Calendar | D84: derived | E84: union of every statutory due date below + every expiry-bearing record (insurance, warranties, DSC) | G84: Derived from the obligations, never kept by hand. A hand-kept calendar is the one document guaranteed to be wrong the year it matters.
A87: THE STATUTORY MIRROR | B87: Every obligation of an Indian LLP, mapped onto the ComplianceEvent object — the governance calendar is derived from these rows, never kept by hand.
A88: Ref | B88: Instrument | C88: Authority | E88: What | F88: Due | G88: Applies when
A89: ST-01 | B89: Form 3 | C89: MCA | E89: File the LLP Agreement and any change to it. | F89: Within 30 days of incorporation or of the change | G89: always
A90: ST-02 | B90: Form 11 | C90: MCA | E90: Annual Return — partners, contributions, changes in the year. | F90: Within 60 days of financial year end (by 30 May) | G90: always
A91: ST-03 | B91: Form 8 | C91: MCA | E91: Statement of Account & Solvency — the accounts CP.9 produces, filed. | F91: By 30 October each year | G91: always
A92: ST-04 | B92: Statutory audit | C92: MCA | E92: Audit of the accounts. | F92: Before Form 8 | G92: turnover > ₹40 lakh OR contribution > ₹25 lakh — every GC vehicle crosses the second test at formation
A93: ST-05 | B93: ITR-5 | C93: Income Tax | E93: Income tax return of the LLP. | F93: 31 July, or 31 October when audited — GC vehicles are audited, so 31 October | G93: always
A94: ST-06 | B94: TDS returns (24Q/26Q) | C94: Income Tax | E94: Quarterly deduction returns against the TAN. | F94: Quarterly | G94: any payment attracting TDS — contractor, professional fees, interest
A95: ST-07 | B95: GST returns | C95: GST | E95: Registration and periodic returns. | F95: Monthly/quarterly per registration | G95: taxable supplies exceed the threshold — expected once operations begin
A96: ST-08 | B96: Form 4 | C96: MCA | E96: Change of partner or designated partner. | F96: Within 30 days of the change | G96: on every admission, resignation or transfer — every settlement that admits a partner fires this
A97: ST-09 | B97: Form 15 | C97: MCA | E97: Change of registered office. | F97: Within 30 days | G97: on relocation
A98: ST-10 | B98: DIR-3 KYC | C98: MCA | E98: Annual KYC of every designated partner's DPIN. | F98: By 30 September each year | G98: always
A99: ST-11 | B99: CRZ clearance conditions | C99: State | E99: Conditions attached to the Coastal Regulation Zone approval — the approval itself is a Property Document (SP.4). | F99: As conditioned | G99: coastal properties — SlowSpace Coastal is one
A101: §33 AMENDMENT QUEUE | B101: Candidate objects the model needs and the ratified 27 do not contain. Ratifying one moves its constituents from `registered` to `object` without restructuring anything. This is Decision D-18.
B102: AllocationRight | C102: needed by 2 constituent(s)
B103: BankAccount | C103: needed by 1 constituent(s)
B104: CapitalAccount | C104: needed by 2 constituent(s)
...
