Workbook

Sheet README
A1: Getaway Collective · LLP Intake Template
A2: Fill one row per LLP on each tab. Row 5 is the worked example and stays.
A4: WHAT THIS REPLACES | B4: Three placeholder properties currently ship in the product: Kyoto House (KYO-01), Swiss Vault (CHE-02) and Oslo Base (NOR-03), in three invented vehicles. They appear on the Collection, the capital register, the gallery, the sitemap and the telemetry board. See the RETIRING tab.
A5: WHAT IT FEEDS | B5: Every column names its destination — file, symbol and UFR registry id — on the FIELD MAP tab. Nothing here is decorative: a blank required cell becomes a blank on a public page or a thrown error at load.
A7: THREE CELL COLOURS
A8: Yellow | B8: You fill it.
A9: Grey | B9: DERIVED — do not type. The application computes it; the column exists so you can check what it will compute.
A10: Cream (row 5) | B10: The worked example: SlowSpace Coastal LLP, already in the codebase. It is the format specimen. Do not delete it.
A12: THE FOUR GOLDEN RULES
A13: 1 · Money is exact | B13: Enter whole rupees, no commas, no symbol, no decimals. 40000000 is ₹4,00,00,000. The application stores money as integers and will not accept a float.
A14: 2 · Percentages are basis points | B14: Enter 1000 for 10.00%, 500 for 5.00%. The waterfall and the ownership ladder are both bps.
A15: 3 · Every forward figure names its confidence | B15: observed · verified · modelled · estimated · forecast · pending. A figure without one does not render. A management estimate is NOT an appraisal, and the product says which it is.
A16: 4 · Dates are ISO | B16: YYYY-MM-DD. Nothing else parses.
A18: BEFORE YOU SEND IT BACK | B18: Open the VALIDATION tab. Every row must read PASS. It reproduces the invariants the application enforces at load — units tiling the equity layer, the waterfall closing to 100%, the night pool dividing without inventing nights. A FAIL here is an error that would otherwise surface as a crash or, worse, as a wrong number on a page an investor reads.
A20: WHAT I STILL CANNOT DO FOR YOU | B20: Verify that an LLP exists. Every LLPIN, registered office and incorporation date on the Vehicle tab must be checked against the MCA register by someone with access to it — that is launch gate G-03 and Decision D-03, and no amount of template discipline substitutes for it.

Sheet 1 Vehicle
A1: 1 · The Vehicle (LLP)
A2: The entity. Everything on this row is a fact about a registered body corporate and must be verifiable against the MCA register — this is the tab launch gate G-03 audits.
A4: LLP key | B4: Registered name | C4: LLPIN | D4: Form | E4: Incorporated | F4: Agreement dated | G4: Registered office | H4: Registrar | I4: PAN | J4: TAN | K4: Lifecycle | L4: Audited?
A5: slowspace | B5: SlowSpace Coastal LLP | C5: AAC-4471 | D5: llp | E5: 2026-06-12 | F5: 2026-06-19 | G5: 2nd Floor, Maruthi Arcade, Udupi 576101, Karnataka | H5: RoC Bangalore | K5: forming | L5: yes
A6: solace | B6: Solace Retreats LLP | D6: llp | H6: RoC Bangalore | K6: forming | L6: no
A7: coorgcreek | B7: Coorg Coffee Creek LLP | D7: llp | H7: RoC Bangalore | K7: raising | L7: no
A27: Add rows below 25 if you have more than twenty vehicles; the VALIDATION tab formulas must be extended to match — tell me and I will extend them.

Sheet 2 Property
A1: 2 · The Property (Domain I · Space)
A2: What the LLP owns: land, build, furniture and fittings. One property per vehicle — the constitutional model is one property, one LLP.
A4: LLP key | B4: Property name | C4: Asset code | D4: Jurisdiction | E4: Coordinates | F4: Title reference | G4: Land area | H4: Keys | I4: Lifecycle | J4: Stabilised on | K4: Commitments | L4: Hue
A5: slowspace | B5: SlowSpace Coastal | C5: PDB-01 | D5: Padubidri, Karnataka | E5: 13.117416°N · 74.765988°E | G5: .3 acres · dual frontage | H5: 12 | I5: development | K5: CRZ compliant · Blue Flag adjacent · modular assembly | L5: 198
A6: solace | B6: Slowspace Solace | C6: CKB-01 | D6: Chikkaballapur, Karnataka | E6: 13°24'40.5"N 77°49'26.9"E | G6: 1.55 acres (0.20 owned + 1.35 leased) | H6: 6 | I6: development | K6: 8 guntas owned (freehold) + 1 acre 14 guntas leased (leasehold). PACK_ARID_HILL Climate Mutation. CONFLICT: Genesis Portfolio Registry (spatial ledger) records Solace site area as 0.6 Acres - roughly a third of this 1.55-acre combined figure. Unreconciled pending Founder confirmation of whether the registry figure was owned-parcel-only or a different planning boundary. | L6: 35
A7: coorgcreek | B7: Coorg Coffee Creek | C7: COG-03 | D7: Coorg, Karnataka | E7: 12°23'25.8"N 75°49'15.2"E | G7: 10 acres (possession) | H7: 20 | I7: acquired | K7: SlowSpace brand. Land held under possession; title/Land Reforms Act/conversion status unverified. Construction financed via a Rs.5.0 Cr facility once the equity raise closes. CONFLICT: Land Area (10 acres) and Studio Count (20) are identical to "The Creek" (Coorg, ESKAPE brand, PACK_RIPARIAN_FOREST) already in the Genesis Portfolio Registry. Unreconciled - confirm this is a distinct sixth estate and not a naming collision or rebrand. | L7: 90

Sheet 3 Capital stack
A1: 3 · The Capital Stack (Domain III · Capital)
A2: Whole rupees. No commas, no symbol, no decimals. Equity clears the land and the approvals before a rupee of debt is drawn, so pre-construction risk sits entirely on equity.
A4: LLP key | B4: Land (₹) | C4: Formation (₹) | D4: Facility (₹) | E4: Equity layer (₹) | F4: Project total (₹) | G4: Moratorium | H4: Lender | I4: Covenant
A5: slowspace | B5: 30000000 | C5: 10000000 | D5: 55000000 | E5: =IF(B5="","",B5+C5) -> 40000000 | F5: =IF(B5="","",E5+D5) -> 95000000 | G5: Interest-only during months 1–18 | I5: DSCR 1.50x minimum
A6: solace | B6: 10000000 | C6: 10000000 | D6: 30000000 | E6: =IF(B6="","",B6+C6) -> 20000000 | F6: =IF(B6="","",E6+D6) -> 50000000 | G6: Interest-only during months 1–18 | I6: DSCR 1.50x minimum
A7: coorgcreek | B7: 60000000 | C7: 40000000 | D7: 50000000 | E7: =IF(B7="","",B7+C7) -> 100000000 | F7: =IF(B7="","",E7+D7) -> 150000000 | G7: Interest-only during months 1-18 | I7: DSCR 1.50x minimum
E8: =IF(B8="","",B8+C8) | F8: =IF(B8="","",E8+D8)
E9: =IF(B9="","",B9+C9) | F9: =IF(B9="","",E9+D9)
E10: =IF(B10="","",B10+C10) | F10: =IF(B10="","",E10+D10)
E11: =IF(B11="","",B11+C11) | F11: =IF(B11="","",E11+D11)
E12: =IF(B12="","",B12+C12) | F12: =IF(B12="","",E12+D12)
E13: =IF(B13="","",B13+C13) | F13: =IF(B13="","",E13+D13)
E14: =IF(B14="","",B14+C14) | F14: =IF(B14="","",E14+D14)
E15: =IF(B15="","",B15+C15) | F15: =IF(B15="","",E15+D15)
E16: =IF(B16="","",B16+C16) | F16: =IF(B16="","",E16+D16)
E17: =IF(B17="","",B17+C17) | F17: =IF(B17="","",E17+D17)
E18: =IF(B18="","",B18+C18) | F18: =IF(B18="","",E18+D18)
E19: =IF(B19="","",B19+C19) | F19: =IF(B19="","",E19+D19)
... E25: =IF(B25="","",B25+C25) | F25: =IF(B25="","",E25+D25)

Sheet 4 Units & ladder
A1: 4 · Ownership Units and the Allocation Ladder | J1: total debt | K1: total project value
A2: Basis points: 500 = 5.00%. The minimum unit is also the increment. The ceiling is a GOVERNANCE limit, not a commercial one — above 50% a single partner carries every ordinary resolution alone (§24a), and the register votes for the record only.
A4: LLP key | B4: Minimum Investment (bps) | C4: Minimum unit (bps) | D4: Step (bps) | E4: Ceiling (bps) | G4: total equity | H4: promoter Investment | I4: Offering | J4: debt | K4: Total Project | L4: Units in vehicle | M4: Unit price (₹) | N4: Units subscribed | O4: Available | P4: Deposit (₹) | Q4: Lock-in
A5: slowspace | B5: 1000 | C5: 500 | D5: 500 | E5: 5000 | G5: 40000000 | H5: 16000000 | I5: =+G5-H5 -> 24000000 | J5: 55000000 | K5: =+G5+J5 -> 95000000 | L5: 6 | M5: =+G5/(B5/100) -> 4000000 | N5: 5 | O5: 1 | P5: 50000 | Q5: 36 months from financial close
A6: solace | B6: 1000 | C6: 500 | D6: 500 | E6: 5000 | G6: 25000000 | H6: 10000000 | I6: =+G6-H6 -> 15000000 | J6: 30000000 | K6: =+G6+J6 -> 55000000 | L6: 4 | M6: =+G6/(B6/100) -> 2500000 | N6: 0 | O6: 4 | P6: 50000 | Q6: 36 months from financial close
A7: coorgcreek | B7: 1000 | C7: 500 | D7: 500 | E7: 6000 | G7: 100000000 | H7: 60000000 | I7: =+G7-H7 -> 40000000 | J7: 50000000 | K7: =+G7+J7 -> 150000000 | L7: =+I7/M7 -> 4 | M7: =+G7/(B7/100) -> 10000000 | N7: 0 | O7: 4 | P7: 50000 | Q7: 36 months from financial close
M8: =IFERROR(IF(#REF!="","",INDEX('3 Capital stack'!$E$5:$E$25,MATCH(A8,'3 Capital stack'!$A$5:$A$25,0))/L8),"")
M9: =IFERROR(IF(#REF!="","",INDEX('3 Capital stack'!$E$5:$E$25,MATCH(A9,'3 Capital stack'!$A$5:$A$25,0))/L9),"")
M10: =IFERROR(IF(#REF!="","",INDEX('3 Capital stack'!$E$5:$E$25,MATCH(A10,'3 Capital stack'!$A$5:$A$25,0))/L10),"")
M11: =IFERROR(IF(#REF!="","",INDEX('3 Capital stack'!$E$5:$E$25,MATCH(A11,'3 Capital stack'!$A$5:$A$25,0))/L11),"")
M12: =IFERROR(IF(#REF!="","",INDEX('3 Capital stack'!$E$5:$E$25,MATCH(A12,'3 Capital stack'!$A$5:$A$25,0))/L12),"")
M13: =IFERROR(IF(#REF!="","",INDEX('3 Capital stack'!$E$5:$E$25,MATCH(A13,'3 Capital stack'!$A$5:$A$25,0))/L13),"")
M14: =IFERROR(IF(#REF!="","",INDEX('3 Capital stack'!$E$5:$E$25,MATCH(A14,'3 Capital stack'!$A$5:$A$25,0))/L14),"")
M15: =IFERROR(IF(#REF!="","",INDEX('3 Capital stack'!$E$5:$E$25,MATCH(A15,'3 Capital stack'!$A$5:$A$25,0))/L15),"")
M16: =IFERROR(IF(#REF!="","",INDEX('3 Capital stack'!$E$5:$E$25,MATCH(A16,'3 Capital stack'!$A$5:$A$25,0))/L16),"")
M17: =IFERROR(IF(#REF!="","",INDEX('3 Capital stack'!$E$5:$E$25,MATCH(A17,'3 Capital stack'!$A$5:$A$25,0))/L17),"")
M18: =IFERROR(IF(#REF!="","",INDEX('3 Capital stack'!$E$5:$E$25,MATCH(A18,'3 Capital stack'!$A$5:$A$25,0))/L18),"")
M19: =IFERROR(IF(#REF!="","",INDEX('3 Capital stack'!$E$5:$E$25,MATCH(A19,'3 Capital stack'!$A$5:$A$25,0))/L19),"")
... M25: =IFERROR(IF(#REF!="","",INDEX('3 Capital stack'!$E$5:$E$25,MATCH(A25,'3 Capital stack'!$A$5:$A$25,0))/L25),"")

Sheet 5 Operating & waterfall
A1: 5 · Operating Assumptions and the Six-Stage Waterfall
A2: The waterfall must close to exactly 100% of gross revenue. Debt service is its OWN stage — folding it inside the investor share shows an investor a number that a quarter of gross leaves before they see it. Stage 6 does not run at all if paying it would take the reserve below its floor.
A4: LLP key | B4: ADR (₹) | C4: Occupancy (bps) | D4: Gross revenue (₹) | E4: 1 Operator (bps) | F4: 2 Brand (bps) | G4: 3 Admin reserve (bps) | H4: 4 Sinking fund (bps) | I4: 5 Debt service (bps) | J4: 6 To partners (bps) | K4: Reserve floor (₹) | L4: Yield confidence
A5: slowspace | B5: 15000 | C5: 5000 | D5: =IFERROR(IF(B5="","",INDEX('2 Property'!$H$5:$H$25,MATCH(A5,'2 Property'!$A$5:$A$25,0))*365*(C5/10000)*B5),"") -> 32850000 | E5: 3500 | F5: 1500 | G5: 250 | H5: 250 | I5: 2308 | J5: =IF(B5="","",10000-E5-F5-G5-H5-I5) -> 2192 | K5: 3960000 | L5: modelled
A6: solace | B6: 12000 | C6: 5000 | D6: =IFERROR(IF(B6="","",INDEX('2 Property'!$H$5:$H$25,MATCH(A6,'2 Property'!$A$5:$A$25,0))*365*(C6/10000)*B6),"") -> 13140000 | E6: 4000 | F6: 1500 | G6: 250 | H6: 250 | I6: 2308 | J6: =IF(B6="","",10000-E6-F6-G6-H6-I6) -> 1692
A7: coorgcreek | B7: 12000 | C7: 5500 | D7: =IFERROR(IF(B7="","",INDEX('2 Property'!$H$5:$H$25,MATCH(A7,'2 Property'!$A$5:$A$25,0))*365*(C7/10000)*B7),"") -> 48180000 | E7: 4000 | F7: 1500 | G7: 250 | H7: 250 | I7: 1500 | J7: =IF(B7="","",10000-E7-F7-G7-H7-I7) -> 2500 | K7: 8700000 | L7: estimated
D8: =IFERROR(IF(B8="","",INDEX('2 Property'!$H$5:$H$25,MATCH(A8,'2 Property'!$A$5:$A$25,0))*365*(C8/10000)*B8),"") | J8: =IF(B8="","",10000-E8-F8-G8-H8-I8)
D9: =IFERROR(IF(B9="","",INDEX('2 Property'!$H$5:$H$25,MATCH(A9,'2 Property'!$A$5:$A$25,0))*365*(C9/10000)*B9),"") | J9: =IF(B9="","",10000-E9-F9-G9-H9-I9)
D10: =IFERROR(IF(B10="","",INDEX('2 Property'!$H$5:$H$25,MATCH(A10,'2 Property'!$A$5:$A$25,0))*365*(C10/10000)*B10),"") | J10: =IF(B10="","",10000-E10-F10-G10-H10-I10)
D11: =IFERROR(IF(B11="","",INDEX('2 Property'!$H$5:$H$25,MATCH(A11,'2 Property'!$A$5:$A$25,0))*365*(C11/10000)*B11),"") | J11: =IF(B11="","",10000-E11-F11-G11-H11-I11)
D12: =IFERROR(IF(B12="","",INDEX('2 Property'!$H$5:$H$25,MATCH(A12,'2 Property'!$A$5:$A$25,0))*365*(C12/10000)*B12),"") | J12: =IF(B12="","",10000-E12-F12-G12-H12-I12)
D13: =IFERROR(IF(B13="","",INDEX('2 Property'!$H$5:$H$25,MATCH(A13,'2 Property'!$A$5:$A$25,0))*365*(C13/10000)*B13),"") | J13: =IF(B13="","",10000-E13-F13-G13-H13-I13)
D14: =IFERROR(IF(B14="","",INDEX('2 Property'!$H$5:$H$25,MATCH(A14,'2 Property'!$A$5:$A$25,0))*365*(C14/10000)*B14),"") | J14: =IF(B14="","",10000-E14-F14-G14-H14-I14)
D15: =IFERROR(IF(B15="","",INDEX('2 Property'!$H$5:$H$25,MATCH(A15,'2 Property'!$A$5:$A$25,0))*365*(C15/10000)*B15),"") | J15: =IF(B15="","",10000-E15-F15-G15-H15-I15)
D16: =IFERROR(IF(B16="","",INDEX('2 Property'!$H$5:$H$25,MATCH(A16,'2 Property'!$A$5:$A$25,0))*365*(C16/10000)*B16),"") | J16: =IF(B16="","",10000-E16-F16-G16-H16-I16)
D17: =IFERROR(IF(B17="","",INDEX('2 Property'!$H$5:$H$25,MATCH(A17,'2 Property'!$A$5:$A$25,0))*365*(C17/10000)*B17),"") | J17: =IF(B17="","",10000-E17-F17-G17-H17-I17)
D18: =IFERROR(IF(B18="","",INDEX('2 Property'!$H$5:$H$25,MATCH(A18,'2 Property'!$A$5:$A$25,0))*365*(C18/10000)*B18),"") | J18: =IF(B18="","",10000-E18-F18-G18-H18-I18)
D19: =IFERROR(IF(B19="","",INDEX('2 Property'!$H$5:$H$25,MATCH(A19,'2 Property'!$A$5:$A$25,0))*365*(C19/10000)*B19),"") | J19: =IF(B19="","",10000-E19-F19-G19-H19-I19)
... D25: =IFERROR(IF(B25="","",INDEX('2 Property'!$H$5:$H$25,MATCH(A25,'2 Property'!$A$5:$A$25,0))*365*(C25/10000)*B25),"") | J25: =IF(B25="","",10000-E25-F25-G25-H25-I25)

Sheet 6 Time
A1: 6 · Entitlement (Domain II · Time)
A2: Time is ownership, not hospitality: a static yearly allocation multiplied by the stake. The POOL is stated for the whole vehicle and each position takes its FLOOR of it, so the sum of every partner's entitlement can never exceed what the property can deliver.
A4: LLP key | B4: Night pool min | C4: Night pool max | D4: Min unit gets | E4: Reserved days | F4: Blackout rules | G4: Entitlement begins | H4: Lapse policy
A5: slowspace | B5: 180 | C5: 210 | D5: =IFERROR(IF(B5="","",FLOOR(B5*INDEX('4 Units & ladder'!#REF!,MATCH(A5,'4 Units & ladder'!$A$5:$A$25,0))/10000,1)),"") | E5: 0 | G5: Handover, Jan 2028
A6: solace | D6: =IFERROR(IF(B6="","",FLOOR(B6*INDEX('4 Units & ladder'!#REF!,MATCH(A6,'4 Units & ladder'!$A$5:$A$25,0))/10000,1)),"")
A7: coorgcreek | B7: 300 | C7: 350 | D7: =IFERROR(IF(B7="","",FLOOR(B7*INDEX('4 Units & ladder'!#REF!,MATCH(A7,'4 Units & ladder'!$A$5:$A$25,0))/10000,1)),"") | E7: 0 | G7: TBD - pending Programme lock (construction not yet started)
D8: =IFERROR(IF(B8="","",FLOOR(B8*INDEX('4 Units & ladder'!#REF!,MATCH(A8,'4 Units & ladder'!$A$5:$A$25,0))/10000,1)),"")
D9: =IFERROR(IF(B9="","",FLOOR(B9*INDEX('4 Units & ladder'!#REF!,MATCH(A9,'4 Units & ladder'!$A$5:$A$25,0))/10000,1)),"")
D10: =IFERROR(IF(B10="","",FLOOR(B10*INDEX('4 Units & ladder'!#REF!,MATCH(A10,'4 Units & ladder'!$A$5:$A$25,0))/10000,1)),"")
D11: =IFERROR(IF(B11="","",FLOOR(B11*INDEX('4 Units & ladder'!#REF!,MATCH(A11,'4 Units & ladder'!$A$5:$A$25,0))/10000,1)),"")
D12: =IFERROR(IF(B12="","",FLOOR(B12*INDEX('4 Units & ladder'!#REF!,MATCH(A12,'4 Units & ladder'!$A$5:$A$25,0))/10000,1)),"")
D13: =IFERROR(IF(B13="","",FLOOR(B13*INDEX('4 Units & ladder'!#REF!,MATCH(A13,'4 Units & ladder'!$A$5:$A$25,0))/10000,1)),"")
D14: =IFERROR(IF(B14="","",FLOOR(B14*INDEX('4 Units & ladder'!#REF!,MATCH(A14,'4 Units & ladder'!$A$5:$A$25,0))/10000,1)),"")
D15: =IFERROR(IF(B15="","",FLOOR(B15*INDEX('4 Units & ladder'!#REF!,MATCH(A15,'4 Units & ladder'!$A$5:$A$25,0))/10000,1)),"")
D16: =IFERROR(IF(B16="","",FLOOR(B16*INDEX('4 Units & ladder'!#REF!,MATCH(A16,'4 Units & ladder'!$A$5:$A$25,0))/10000,1)),"")
D17: =IFERROR(IF(B17="","",FLOOR(B17*INDEX('4 Units & ladder'!#REF!,MATCH(A17,'4 Units & ladder'!$A$5:$A$25,0))/10000,1)),"")
D18: =IFERROR(IF(B18="","",FLOOR(B18*INDEX('4 Units & ladder'!#REF!,MATCH(A18,'4 Units & ladder'!$A$5:$A$25,0))/10000,1)),"")
D19: =IFERROR(IF(B19="","",FLOOR(B19*INDEX('4 Units & ladder'!#REF!,MATCH(A19,'4 Units & ladder'!$A$5:$A$25,0))/10000,1)),"")
... D25: =IFERROR(IF(B25="","",FLOOR(B25*INDEX('4 Units & ladder'!#REF!,MATCH(A25,'4 Units & ladder'!$A$5:$A$25,0))/10000,1)),"")

Sheet 7 Governance
A1: 7 · Governance (Domain IV · the constitutional layer)
A2: Voting is contribution-weighted, never per capita. A TIE IS NOT APPROVAL — an ordinary resolution needs MORE than half, so an uncast vote has a real consequence.
A4: LLP key | B4: Ordinary (bps) | C4: Special (bps) | D4: Quorum (bps) | E4: Reserved matters | F4: Transfer rule | G4: Designated partners
A5: slowspace | B5: 5001 | C5: 7600 | D5: 6000 | E5: Disposing of the land, or borrowing beyond ₹6.0 Cr | F5: Internal register first; external buyer needs consent | G5: Getaway Collective (GP)
A6: solace
A7: coorgcreek | B7: 5001 | C7: 7600 | D7: 6000 | E7: Disposing of the land, or borrowing beyond Rs.6.0 Cr | F7: Internal register first; external buyer needs consent | G7: Getaway Collective (GP)

Sheet 8 Programme
A1: 8 · Programme — many rows per LLP
A2: Design to handover. One row per stage, in order. Shown to investors on the offering and tracked in the console; a delay here becomes a notice, not a surprise.
A4: LLP key | B4: Window | C4: Stage | D4: Capital state | E4: Detail | F4: Current?
A5: slowspace | B5: Jul – Oct 2026 | C5: Design & Approvals | D5: Pre-construction | E5: CRZ compliance, IDO model locked, hardware/software mapping. | F5: yes
A6: slowspace | B6: Nov – Dec 2026 | C6: Construction start | D6: Debt drawdown begins | E6: Structural grid hardwired, modular assembly begins. | F6: no
A7: slowspace | B7: Jan – Oct 2027 | C7: Assembly & fit-out | D7: Peak deployment | E7: Superstructure, acoustic sealing, unit integration. | F7: no
A8: slowspace | B8: Nov 2027 – Jan 2028 | C8: Handover | D8: Settlement | E8: Autonomous systems test, handover, open for occupancy. | F8: no

Sheet 9 Risk disclosure
A1: 9 · Asset Disclosure — many rows per LLP
A2: The per-property disclosure an investor must reach the end of before the commitment opens. Measured and specific: facts do the work. Every figure beside an item is READ FROM THE VEHICLE RECORD, never retyped — restating commercial terms in prose is how prose drifts from the instrument it describes.
A4: LLP key | B4: No. | C4: Title | D4: Paragraph 1 | E4: Paragraph 2 | F4: Paragraph 3 | G4: Fact label | H4: Fact value
A5: slowspace | B5: 02 | C5: Development & Construction | D5: This hospitality asset is currently in its development phase. | E5: Construction, statutory approvals and commissioning must all be completed before the property begins generating operating income. | F5: Development projects may be subject to delays, cost increases or programme revisions that affect the timing of operations. | G5: Moratorium | H5: Interest-only during months 1–18
A6: slowspace | B6: 03 | C6: Market & Competitive Positioning | D6: Seaside Confluence is positioned above the premium private-villa segment and below ultra-luxury boutique competitors in the Udupi-Padubidri corridor. | E6: Achieved average daily rate depends on maintaining this positioning against comparable coastal properties across a stated range of Rs.15,000-20,000 in the off-season and Rs.28,000-60,000+ in peak season. | F6: There is no assurance that targeted occupancy will be achieved or sustained at the levels modelled in this register. | G6: Target ADR | H6: Rs.15,000 (Operating & waterfall tab, blended assumption)
A7: slowspace | B7: 04 | C7: Leverage & Debt Servicing | D7: The facility layer is drawn only during construction and is serviced against a minimum covenant of 1.50x DSCR. | E7: Debt service is calculated as its own stage of the revenue waterfall, ahead of any distribution to partners. | F7: A shortfall in occupancy or ADR against the modelled case would compress the amount available for the partner distribution stage before it would affect debt service. | G7: Debt service (bps) | H7: 2,308 bps of gross revenue
A8: solace | B8: 01 | C8: Mixed Tenure - Owned and Leasehold Parcels | D8: The Solace site comprises two parcels: 8 guntas held freehold and 1 acre 14 guntas held on lease. | E8: The leasehold parcel is subject to the terms of a lease agreement whose expiry, renewal and rent-escalation terms have not yet been entered into this register. | F8: Continued site control depends in part on the lease remaining in force; loss or non-renewal of the leasehold parcel would reduce the site below its currently modelled footprint. | G8: Land area | H8: 1.55 acres (0.20 owned + 1.35 leased)
A9: coorgcreek | B9: 01 | C9: Land Tenure - Possession, Not Registered Title | D9: The 10-acre Coorg site is held under possession. Registered title, and any Land Reforms Act ceiling or non-agriculturist conversion status, have not yet been verified against the relevant government record. | E9: The Rs.6.0 Cr land value used to size the equity layer in this register is a management estimate, not an appraisal or a valuation performed against confirmed title. | F9: A title or conversion defect could affect the LLP's ability to hold, develop, or mortgage the land as contemplated in the capital stack and facility. | G9: Land value (management estimate) | H9: Rs.6,00,00,000
A10: coorgcreek | B10: 02 | C10: Development Stage - Pre-Construction, Capital Raise Open | D10: This hospitality asset has not yet begun construction. The equity tranche referenced in this register is being raised and is not yet fully subscribed. | E10: The construction facility has not yet been drawn and is contingent on the equity raise closing and statutory approvals being obtained. | F10: Development projects may be subject to delays, cost increases, or programme revisions that affect the timing and quantum of both distributions and unit entitlements. | G10: Units subscribed | H10: 12 of 20 (founder land-in-kind allocation; investor tranche open)
A27: TOTAL LOSS IS STATED SEPARATELY AND LAST — it is not an item in this list. A numbered item invites a reader to weigh it against its neighbours; that one is not comparable, and standing outside the sequence is how the layout says so. It is already written and applies to every vehicle.

Sheet 10 Plates
A1: 10 · Plates — many rows per property
A2: Every plate states WHAT IT IS. A render presented as a photograph is the commonest misrepresentation in this industry, and the kind field has no default for that reason.
A4: LLP key | B4: Ref | C4: Kind | D4: Caption | E4: Taken / made on | F4: Credit / licence | G4: File
A5: slowspace | B5: F-01 | C5: drawing | D5: Section through the western edge. The wall thickness is the acoustic decision. | E5: 2026-06-19

Sheet VALIDATION
A1: Validation — every row must read PASS
A2: These reproduce the invariants the application enforces at load. A FAIL here is an error that would otherwise surface as a crash, or — worse — as a wrong number on a page an investor reads.
A4: LLP key | B4: Units tile 10000 | C4: Unit price whole ₹ | D4: Stages 1-5 leave room | E4: Stage 6 > 0 | F4: Nights don't inflate | G4: Subscribed ≤ units | H4: What a FAIL means
A5: ='1 Vehicle'!A5 -> slowspace | B5: =IF('4 Units & ladder'!B5="","",IF(MOD(10000,'4 Units & ladder'!B5)=0,"PASS","FAIL")) -> PASS | C5: =IF('4 Units & ladder'!M5="","",IF(MOD('4 Units & ladder'!M5,1)=0,"PASS","FAIL")) -> PASS | D5: =IF('5 Operating & waterfall'!E5="","",IF(AND('5 Operating & waterfall'!E5>0,'5 Operating & waterfall'!F5>0,'5 Operating & waterfall'!G5>0,'5 Operating & waterfall'!H5>0,'5 Operating & waterfall'!I5>0,'5 Operating & waterfall'!E5+'5 Operating & waterfall'!F5+'5 Operating & waterfall'!G5+'5 Operating & waterfall'!H5+'5 Operating & waterfall'!I5<10000),"PASS","FAIL")) -> PASS | E5: =IF('5 Operating & waterfall'!J5="","",IF('5 Operating & waterfall'!J5>0,"PASS","FAIL")) -> PASS | F5: =IF('6 Time'!D5="","",IF('6 Time'!D5*'4 Units & ladder'!L5<='6 Time'!C5,"PASS","FAIL")) | G5: =IF('4 Units & ladder'!N5="","",IF('4 Units & ladder'!N5<='4 Units & ladder'!L5,"PASS","FAIL")) -> PASS
A6: ='1 Vehicle'!A6 -> solace | B6: =IF('4 Units & ladder'!B6="","",IF(MOD(10000,'4 Units & ladder'!B6)=0,"PASS","FAIL")) -> PASS | C6: =IF('4 Units & ladder'!M6="","",IF(MOD('4 Units & ladder'!M6,1)=0,"PASS","FAIL")) -> PASS | D6: =IF('5 Operating & waterfall'!E6="","",IF(AND('5 Operating & waterfall'!E6>0,'5 Operating & waterfall'!F6>0,'5 Operating & waterfall'!G6>0,'5 Operating & waterfall'!H6>0,'5 Operating & waterfall'!I6>0,'5 Operating & waterfall'!E6+'5 Operating & waterfall'!F6+'5 Operating & waterfall'!G6+'5 Operating & waterfall'!H6+'5 Operating & waterfall'!I6<10000),"PASS","FAIL")) -> PASS | E6: =IF('5 Operating & waterfall'!J6="","",IF('5 Operating & waterfall'!J6>0,"PASS","FAIL")) -> PASS | F6: =IF('6 Time'!D6="","",IF('6 Time'!D6*'4 Units & ladder'!L6<='6 Time'!C6,"PASS","FAIL")) | G6: =IF('4 Units & ladder'!N6="","",IF('4 Units & ladder'!N6<='4 Units & ladder'!L6,"PASS","FAIL")) -> PASS
A7: ='1 Vehicle'!A7 -> coorgcreek | B7: =IF('4 Units & ladder'!B7="","",IF(MOD(10000,'4 Units & ladder'!B7)=0,"PASS","FAIL")) -> PASS | C7: =IF('4 Units & ladder'!M7="","",IF(MOD('4 Units & ladder'!M7,1)=0,"PASS","FAIL")) -> PASS | D7: =IF('5 Operating & waterfall'!E7="","",IF(AND('5 Operating & waterfall'!E7>0,'5 Operating & waterfall'!F7>0,'5 Operating & waterfall'!G7>0,'5 Operating & waterfall'!H7>0,'5 Operating & waterfall'!I7>0,'5 Operating & waterfall'!E7+'5 Operating & waterfall'!F7+'5 Operating & waterfall'!G7+'5 Operating & waterfall'!H7+'5 Operating & waterfall'!I7<10000),"PASS","FAIL")) -> PASS | E7: =IF('5 Operating & waterfall'!J7="","",IF('5 Operating & waterfall'!J7>0,"PASS","FAIL")) -> PASS | F7: =IF('6 Time'!D7="","",IF('6 Time'!D7*'4 Units & ladder'!L7<='6 Time'!C7,"PASS","FAIL")) | G7: =IF('4 Units & ladder'!N7="","",IF('4 Units & ladder'!N7<='4 Units & ladder'!L7,"PASS","FAIL")) -> PASS
A8: ='1 Vehicle'!A8 -> 0 | B8: =IF('4 Units & ladder'!#REF!="","",IF(MOD(10000,'4 Units & ladder'!#REF!)=0,"PASS","FAIL")) -> #REF! | C8: =IF('4 Units & ladder'!M8="","",IF(MOD('4 Units & ladder'!M8,1)=0,"PASS","FAIL")) | D8: =IF('5 Operating & waterfall'!E8="","",IF(AND('5 Operating & waterfall'!E8>0,'5 Operating & waterfall'!F8>0,'5 Operating & waterfall'!G8>0,'5 Operating & waterfall'!H8>0,'5 Operating & waterfall'!I8>0,'5 Operating & waterfall'!E8+'5 Operating & waterfall'!F8+'5 Operating & waterfall'!G8+'5 Operating & waterfall'!H8+'5 Operating & waterfall'!I8<10000),"PASS","FAIL")) | E8: =IF('5 Operating & waterfall'!J8="","",IF('5 Operating & waterfall'!J8>0,"PASS","FAIL")) | F8: =IF('6 Time'!D8="","",IF('6 Time'!D8*'4 Units & ladder'!L8<='6 Time'!C8,"PASS","FAIL")) | G8: =IF('4 Units & ladder'!N8="","",IF('4 Units & ladder'!N8<='4 Units & ladder'!L8,"PASS","FAIL"))
A9: ='1 Vehicle'!A9 -> 0 | B9: =IF('4 Units & ladder'!#REF!="","",IF(MOD(10000,'4 Units & ladder'!#REF!)=0,"PASS","FAIL")) -> #REF! | C9: =IF('4 Units & ladder'!M9="","",IF(MOD('4 Units & ladder'!M9,1)=0,"PASS","FAIL")) | D9: =IF('5 Operating & waterfall'!E9="","",IF(AND('5 Operating & waterfall'!E9>0,'5 Operating & waterfall'!F9>0,'5 Operating & waterfall'!G9>0,'5 Operating & waterfall'!H9>0,'5 Operating & waterfall'!I9>0,'5 Operating & waterfall'!E9+'5 Operating & waterfall'!F9+'5 Operating & waterfall'!G9+'5 Operating & waterfall'!H9+'5 Operating & waterfall'!I9<10000),"PASS","FAIL")) | E9: =IF('5 Operating & waterfall'!J9="","",IF('5 Operating & waterfall'!J9>0,"PASS","FAIL")) | F9: =IF('6 Time'!D9="","",IF('6 Time'!D9*'4 Units & ladder'!L9<='6 Time'!C9,"PASS","FAIL")) | G9: =IF('4 Units & ladder'!N9="","",IF('4 Units & ladder'!N9<='4 Units & ladder'!L9,"PASS","FAIL"))
A10: ='1 Vehicle'!A10 -> 0 | B10: =IF('4 Units & ladder'!#REF!="","",IF(MOD(10000,'4 Units & ladder'!#REF!)=0,"PASS","FAIL")) -> #REF! | C10: =IF('4 Units & ladder'!M10="","",IF(MOD('4 Units & ladder'!M10,1)=0,"PASS","FAIL")) | D10: =IF('5 Operating & waterfall'!E10="","",IF(AND('5 Operating & waterfall'!E10>0,'5 Operating & waterfall'!F10>0,'5 Operating & waterfall'!G10>0,'5 Operating & waterfall'!H10>0,'5 Operating & waterfall'!I10>0,'5 Operating & waterfall'!E10+'5 Operating & waterfall'!F10+'5 Operating & waterfall'!G10+'5 Operating & waterfall'!H10+'5 Operating & waterfall'!I10<10000),"PASS","FAIL")) | E10: =IF('5 Operating & waterfall'!J10="","",IF('5 Operating & waterfall'!J10>0,"PASS","FAIL")) | F10: =IF('6 Time'!D10="","",IF('6 Time'!D10*'4 Units & ladder'!L10<='6 Time'!C10,"PASS","FAIL")) | G10: =IF('4 Units & ladder'!N10="","",IF('4 Units & ladder'!N10<='4 Units & ladder'!L10,"PASS","FAIL"))
A11: ='1 Vehicle'!A11 -> 0 | B11: =IF('4 Units & ladder'!#REF!="","",IF(MOD(10000,'4 Units & ladder'!#REF!)=0,"PASS","FAIL")) -> #REF! | C11: =IF('4 Units & ladder'!M11="","",IF(MOD('4 Units & ladder'!M11,1)=0,"PASS","FAIL")) | D11: =IF('5 Operating & waterfall'!E11="","",IF(AND('5 Operating & waterfall'!E11>0,'5 Operating & waterfall'!F11>0,'5 Operating & waterfall'!G11>0,'5 Operating & waterfall'!H11>0,'5 Operating & waterfall'!I11>0,'5 Operating & waterfall'!E11+'5 Operating & waterfall'!F11+'5 Operating & waterfall'!G11+'5 Operating & waterfall'!H11+'5 Operating & waterfall'!I11<10000),"PASS","FAIL")) | E11: =IF('5 Operating & waterfall'!J11="","",IF('5 Operating & waterfall'!J11>0,"PASS","FAIL")) | F11: =IF('6 Time'!D11="","",IF('6 Time'!D11*'4 Units & ladder'!L11<='6 Time'!C11,"PASS","FAIL")) | G11: =IF('4 Units & ladder'!N11="","",IF('4 Units & ladder'!N11<='4 Units & ladder'!L11,"PASS","FAIL"))
A12: ='1 Vehicle'!A12 -> 0 | B12: =IF('4 Units & ladder'!#REF!="","",IF(MOD(10000,'4 Units & ladder'!#REF!)=0,"PASS","FAIL")) -> #REF! | C12: =IF('4 Units & ladder'!M12="","",IF(MOD('4 Units & ladder'!M12,1)=0,"PASS","FAIL")) | D12: =IF('5 Operating & waterfall'!E12="","",IF(AND('5 Operating & waterfall'!E12>0,'5 Operating & waterfall'!F12>0,'5 Operating & waterfall'!G12>0,'5 Operating & waterfall'!H12>0,'5 Operating & waterfall'!I12>0,'5 Operating & waterfall'!E12+'5 Operating & waterfall'!F12+'5 Operating & waterfall'!G12+'5 Operating & waterfall'!H12+'5 Operating & waterfall'!I12<10000),"PASS","FAIL")) | E12: =IF('5 Operating & waterfall'!J12="","",IF('5 Operating & waterfall'!J12>0,"PASS","FAIL")) | F12: =IF('6 Time'!D12="","",IF('6 Time'!D12*'4 Units & ladder'!L12<='6 Time'!C12,"PASS","FAIL")) | G12: =IF('4 Units & ladder'!N12="","",IF('4 Units & ladder'!N12<='4 Units & ladder'!L12,"PASS","FAIL"))
A13: ='1 Vehicle'!A13 -> 0 | B13: =IF('4 Units & ladder'!#REF!="","",IF(MOD(10000,'4 Units & ladder'!#REF!)=0,"PASS","FAIL")) -> #REF! | C13: =IF('4 Units & ladder'!M13="","",IF(MOD('4 Units & ladder'!M13,1)=0,"PASS","FAIL")) | D13: =IF('5 Operating & waterfall'!E13="","",IF(AND('5 Operating & waterfall'!E13>0,'5 Operating & waterfall'!F13>0,'5 Operating & waterfall'!G13>0,'5 Operating & waterfall'!H13>0,'5 Operating & waterfall'!I13>0,'5 Operating & waterfall'!E13+'5 Operating & waterfall'!F13+'5 Operating & waterfall'!G13+'5 Operating & waterfall'!H13+'5 Operating & waterfall'!I13<10000),"PASS","FAIL")) | E13: =IF('5 Operating & waterfall'!J13="","",IF('5 Operating & waterfall'!J13>0,"PASS","FAIL")) | F13: =IF('6 Time'!D13="","",IF('6 Time'!D13*'4 Units & ladder'!L13<='6 Time'!C13,"PASS","FAIL")) | G13: =IF('4 Units & ladder'!N13="","",IF('4 Units & ladder'!N13<='4 Units & ladder'!L13,"PASS","FAIL"))
A14: ='1 Vehicle'!A14 -> 0 | B14: =IF('4 Units & ladder'!#REF!="","",IF(MOD(10000,'4 Units & ladder'!#REF!)=0,"PASS","FAIL")) -> #REF! | C14: =IF('4 Units & ladder'!M14="","",IF(MOD('4 Units & ladder'!M14,1)=0,"PASS","FAIL")) | D14: =IF('5 Operating & waterfall'!E14="","",IF(AND('5 Operating & waterfall'!E14>0,'5 Operating & waterfall'!F14>0,'5 Operating & waterfall'!G14>0,'5 Operating & waterfall'!H14>0,'5 Operating & waterfall'!I14>0,'5 Operating & waterfall'!E14+'5 Operating & waterfall'!F14+'5 Operating & waterfall'!G14+'5 Operating & waterfall'!H14+'5 Operating & waterfall'!I14<10000),"PASS","FAIL")) | E14: =IF('5 Operating & waterfall'!J14="","",IF('5 Operating & waterfall'!J14>0,"PASS","FAIL")) | F14: =IF('6 Time'!D14="","",IF('6 Time'!D14*'4 Units & ladder'!L14<='6 Time'!C14,"PASS","FAIL")) | G14: =IF('4 Units & ladder'!N14="","",IF('4 Units & ladder'!N14<='4 Units & ladder'!L14,"PASS","FAIL"))
A15: ='1 Vehicle'!A15 -> 0 | B15: =IF('4 Units & ladder'!#REF!="","",IF(MOD(10000,'4 Units & ladder'!#REF!)=0,"PASS","FAIL")) -> #REF! | C15: =IF('4 Units & ladder'!M15="","",IF(MOD('4 Units & ladder'!M15,1)=0,"PASS","FAIL")) | D15: =IF('5 Operating & waterfall'!E15="","",IF(AND('5 Operating & waterfall'!E15>0,'5 Operating & waterfall'!F15>0,'5 Operating & waterfall'!G15>0,'5 Operating & waterfall'!H15>0,'5 Operating & waterfall'!I15>0,'5 Operating & waterfall'!E15+'5 Operating & waterfall'!F15+'5 Operating & waterfall'!G15+'5 Operating & waterfall'!H15+'5 Operating & waterfall'!I15<10000),"PASS","FAIL")) | E15: =IF('5 Operating & waterfall'!J15="","",IF('5 Operating & waterfall'!J15>0,"PASS","FAIL")) | F15: =IF('6 Time'!D15="","",IF('6 Time'!D15*'4 Units & ladder'!L15<='6 Time'!C15,"PASS","FAIL")) | G15: =IF('4 Units & ladder'!N15="","",IF('4 Units & ladder'!N15<='4 Units & ladder'!L15,"PASS","FAIL"))
A16: ='1 Vehicle'!A16 -> 0 | B16: =IF('4 Units & ladder'!#REF!="","",IF(MOD(10000,'4 Units & ladder'!#REF!)=0,"PASS","FAIL")) -> #REF! | C16: =IF('4 Units & ladder'!M16="","",IF(MOD('4 Units & ladder'!M16,1)=0,"PASS","FAIL")) | D16: =IF('5 Operating & waterfall'!E16="","",IF(AND('5 Operating & waterfall'!E16>0,'5 Operating & waterfall'!F16>0,'5 Operating & waterfall'!G16>0,'5 Operating & waterfall'!H16>0,'5 Operating & waterfall'!I16>0,'5 Operating & waterfall'!E16+'5 Operating & waterfall'!F16+'5 Operating & waterfall'!G16+'5 Operating & waterfall'!H16+'5 Operating & waterfall'!I16<10000),"PASS","FAIL")) | E16: =IF('5 Operating & waterfall'!J16="","",IF('5 Operating & waterfall'!J16>0,"PASS","FAIL")) | F16: =IF('6 Time'!D16="","",IF('6 Time'!D16*'4 Units & ladder'!L16<='6 Time'!C16,"PASS","FAIL")) | G16: =IF('4 Units & ladder'!N16="","",IF('4 Units & ladder'!N16<='4 Units & ladder'!L16,"PASS","FAIL"))
A17: ='1 Vehicle'!A17 -> 0 | B17: =IF('4 Units & ladder'!#REF!="","",IF(MOD(10000,'4 Units & ladder'!#REF!)=0,"PASS","FAIL")) -> #REF! | C17: =IF('4 Units & ladder'!M17="","",IF(MOD('4 Units & ladder'!M17,1)=0,"PASS","FAIL")) | D17: =IF('5 Operating & waterfall'!E17="","",IF(AND('5 Operating & waterfall'!E17>0,'5 Operating & waterfall'!F17>0,'5 Operating & waterfall'!G17>0,'5 Operating & waterfall'!H17>0,'5 Operating & waterfall'!I17>0,'5 Operating & waterfall'!E17+'5 Operating & waterfall'!F17+'5 Operating & waterfall'!G17+'5 Operating & waterfall'!H17+'5 Operating & waterfall'!I17<10000),"PASS","FAIL")) | E17: =IF('5 Operating & waterfall'!J17="","",IF('5 Operating & waterfall'!J17>0,"PASS","FAIL")) | F17: =IF('6 Time'!D17="","",IF('6 Time'!D17*'4 Units & ladder'!L17<='6 Time'!C17,"PASS","FAIL")) | G17: =IF('4 Units & ladder'!N17="","",IF('4 Units & ladder'!N17<='4 Units & ladder'!L17,"PASS","FAIL"))
A18: ='1 Vehicle'!A18 -> 0 | B18: =IF('4 Units & ladder'!#REF!="","",IF(MOD(10000,'4 Units & ladder'!#REF!)=0,"PASS","FAIL")) -> #REF! | C18: =IF('4 Units & ladder'!M18="","",IF(MOD('4 Units & ladder'!M18,1)=0,"PASS","FAIL")) | D18: =IF('5 Operating & waterfall'!E18="","",IF(AND('5 Operating & waterfall'!E18>0,'5 Operating & waterfall'!F18>0,'5 Operating & waterfall'!G18>0,'5 Operating & waterfall'!H18>0,'5 Operating & waterfall'!I18>0,'5 Operating & waterfall'!E18+'5 Operating & waterfall'!F18+'5 Operating & waterfall'!G18+'5 Operating & waterfall'!H18+'5 Operating & waterfall'!I18<10000),"PASS","FAIL")) | E18: =IF('5 Operating & waterfall'!J18="","",IF('5 Operating & waterfall'!J18>0,"PASS","FAIL")) | F18: =IF('6 Time'!D18="","",IF('6 Time'!D18*'4 Units & ladder'!L18<='6 Time'!C18,"PASS","FAIL")) | G18: =IF('4 Units & ladder'!N18="","",IF('4 Units & ladder'!N18<='4 Units & ladder'!L18,"PASS","FAIL"))
A19: ='1 Vehicle'!A19 -> 0 | B19: =IF('4 Units & ladder'!#REF!="","",IF(MOD(10000,'4 Units & ladder'!#REF!)=0,"PASS","FAIL")) -> #REF! | C19: =IF('4 Units & ladder'!M19="","",IF(MOD('4 Units & ladder'!M19,1)=0,"PASS","FAIL")) | D19: =IF('5 Operating & waterfall'!E19="","",IF(AND('5 Operating & waterfall'!E19>0,'5 Operating & waterfall'!F19>0,'5 Operating & waterfall'!G19>0,'5 Operating & waterfall'!H19>0,'5 Operating & waterfall'!I19>0,'5 Operating & waterfall'!E19+'5 Operating & waterfall'!F19+'5 Operating & waterfall'!G19+'5 Operating & waterfall'!H19+'5 Operating & waterfall'!I19<10000),"PASS","FAIL")) | E19: =IF('5 Operating & waterfall'!J19="","",IF('5 Operating & waterfall'!J19>0,"PASS","FAIL")) | F19: =IF('6 Time'!D19="","",IF('6 Time'!D19*'4 Units & ladder'!L19<='6 Time'!C19,"PASS","FAIL")) | G19: =IF('4 Units & ladder'!N19="","",IF('4 Units & ladder'!N19<='4 Units & ladder'!L19,"PASS","FAIL"))
... A25: ='1 Vehicle'!A25 -> 0 | B25: =IF('4 Units & ladder'!#REF!="","",IF(MOD(10000,'4 Units & ladder'!#REF!)=0,"PASS","FAIL")) -> #REF! | C25: =IF('4 Units & ladder'!M25="","",IF(MOD('4 Units & ladder'!M25,1)=0,"PASS","FAIL")) | D25: =IF('5 Operating & waterfall'!E25="","",IF(AND('5 Operating & waterfall'!E25>0,'5 Operating & waterfall'!F25>0,'5 Operating & waterfall'!G25>0,'5 Operating & waterfall'!H25>0,'5 Operating & waterfall'!I25>0,'5 Operating & waterfall'!E25+'5 Operating & waterfall'!F25+'5 Operating & waterfall'!G25+'5 Operating & waterfall'!H25+'5 Operating & waterfall'!I25<10000),"PASS","FAIL")) | E25: =IF('5 Operating & waterfall'!J25="","",IF('5 Operating & waterfall'!J25>0,"PASS","FAIL")) | F25: =IF('6 Time'!D25="","",IF('6 Time'!D25*'4 Units & ladder'!L25<='6 Time'!C25,"PASS","FAIL")) | G25: =IF('4 Units & ladder'!N25="","",IF('4 Units & ladder'!N25<='4 Units & ladder'!L25,"PASS","FAIL"))
A27: WHAT EACH CHECK PROTECTS
A28: Units tile 10000 | B28: 10000 / minimum-unit must be a whole number, or the ladder cannot tile the vehicle.
A29: Unit price whole ₹ | B29: The equity layer must divide into whole rupees per unit. A fractional unit price means somebody is short.
A30: Stages 1-5 leave room | B30: Every entered stage must be positive and the five together must leave room for stage 6. Testing that all SIX sum to 100% would be tautological — stage 6 is the remainder — and the first version of this check was exactly that. It passed a row summing to 109%.
A31: Stage 6 > 0 | B31: If stage 6 is zero or negative, partners receive nothing and the offering says otherwise.
A32: Nights don't inflate | B32: units × floor(pool × unit-bps / 10000) must not exceed the pool, or the vehicle promises nights the property cannot deliver.
A33: Subscribed ≤ units | B33: Units subscribed cannot exceed units issued.

Sheet RETIRING
A1: What this replaces
A2: The three placeholder properties currently shipping, and every surface they appear on. When your rows land, these are deleted — not hidden.
A4: Property | B4: Code | C4: Vehicle (invented) | D4: Jurisdiction | E4: Valuation shown | F4: Appears on
A5: Kyoto House | B5: KYO-01 | C5: Coastal Collection SPV I | D5: Kyoto, Japan | E5: ₹12,40,00,000 | F5: /collection · /collection/kyoto-house (+5 sub-pages) · /capital/properties · /admin/telemetry · gallery plate F-03 · sitemap
A6: Swiss Vault | B6: CHE-02 | C6: Alpine Collection SPV II | D6: Valais, Switzerland | E6: ₹18,65,00,000 | F6: /collection · /collection/swiss-vault (+5) · /capital/properties · /admin/telemetry · gallery plate F-04 · sitemap
A7: Oslo Base | B7: NOR-03 | C7: Nordic Collection SPV I | D7: Vestland, Norway | E7: ₹9,82,00,000 | F7: /collection · /collection/oslo-base (+5) · /capital/properties · /admin/telemetry · gallery plate F-05 · sitemap
A9: SlowSpace Coastal LLP (PDB-01, Padubidri) is REAL in the model and stays — it is the worked vehicle the whole commitment flow runs on. Its LLPIN and registered office still need verifying against the MCA register (gate G-03).
A11: The three above are invented. They carry invented valuations from invented valuers, and two of them claim to be stabilised assets acquired years ago. Nothing about them is true, and they are indexable today.

Sheet FIELD MAP
A1: Where every column lands
A2: The import is mechanical because each column has exactly one destination. This is the tab to check if you want to know what a cell actually changes.
A4: Tab | B4: Column | C4: Destination in code | D4: Symbol | E4: Registry id
A5: 1 Vehicle | B5: Registered name | C5: app/_assemblies/slowspace.ts | D5: LLP.name | E5: UFR-0020
A6: 1 Vehicle | B6: LLPIN | C6: app/_assemblies/slowspace.ts | D6: LLP.llpin | E6: —
A7: 1 Vehicle | B7: Incorporated / Agreement | C7: app/_assemblies/slowspace.ts | D7: LLP.incorporated / agreementDated | E7: —
A8: 1 Vehicle | B8: Registered office | C8: app/_assemblies/slowspace.ts | D8: LLP.office | E8: —
A9: 1 Vehicle | B9: Form | C9: constants/ufr.ts enum | D9: vehicle_form | E9: UFR-0021
A10: 1 Vehicle | B10: Lifecycle | C10: constants/ufr.ts enum | D10: lifecycle_state | E10: UFR-0027
A11: 1 Vehicle | B11: Audited? | C11: constants/vehicle-domain.ts | D11: STATUTORY_MIRROR ST-04/ST-05 | E11: —
A12: 2 Property | B12: Property name | C12: app/_assemblies/data.ts | D12: Property.ufr0060 | E12: UFR-0060
A13: 2 Property | B13: Asset code | C13: app/_assemblies/data.ts | D13: Property.assetId | E13: —
A14: 2 Property | B14: Jurisdiction | C14: app/_assemblies/data.ts | D14: Property.ufr0063 | E14: UFR-0063
A15: 2 Property | B15: Title reference | C15: constants/ufr.ts | D15: title_reference | E15: UFR-0064
... A39: 10 Plates | B39: All columns | C39: content/gateway.ts | D39: FRAMES | E39: —
